Workbook

Sheet Respuestas de formulario 1
A1: Marca temporal | B1: NOMBRE DE QUIEN REALIZA LA INSPECCIÓN | C1: CONTRATO | D1: CAMPO/COORDINACIÓN | E1: PLACA DEL VEHICULO | F1: KILOMETRAJE | G1: TURNO | H1: **Altas y bajas | I1: **Direccionales derecha e izquierda | J1: **De parqueo | K1: **De freno | L1: **De reversa y alarma de retroceso | M1: **Espejo central y espejos laterales | N1: **Vidrio frontal | O1: Presentación de orden y aseo | P1: Pito | Q1: Sistema de monitoreo GPS | R1: **Cinturones de seguridad | S1: Puertas en buen estado | T1: Vidrios en buen estado | U1: Limpia brisas | V1: Exintor vigente | W1: Botiquín | X1: Estado general de tapicería | Y1: Indicadores (nivel de combustible, temperatura, velocímetro y aceite) | Z1: **Verificar la ausencia de objetos sueltos en la cabina que puedan distraer al conductor | AA1: **Frenos | AB1: **Freno de emergencia o de mano | AC1: **Fugas de aire (movil 100) | AD1: **Control fugas de aire (movil 100) | AE1: **Candados y Bandas (movil 100) | AF1: **Acoples para tomas eléctricas y de aire (movil 100) | AG1: **Niveles de fluidos aceite motor | AH1: **Nivel de fluido de frenos | AI1: **Nivel de fluido de dirección hidraúlica | AJ1: **Nivel de fluido refrigerante | AK1: Nivel de fluido limpia parabrisas | AL1: Estado de correas | AM1: Estado de baterías, cables, conexiones | AN1: **Llantas - Labrado (min 3mm de labrado) | AO1: **Llantas - Sin cortaduras y sin abultamientos | AP1: Llanta de repuesto | AQ1: **Copas o pernos de sujeción de las llantas | AR1: **Suspensión (terminales) | AS1: **Dirección (terminales) | AT1: Tapa de tanque de combustible en buen estado | AU1: Equipo de carretera: gato, llave de pernos, herramienta básica, triángulos o conos, bloques, chaleco, señal pare-siga | AV1: Kit ambiental | AW1: Documentación: tecnomecánica y de gases, tarjeta de propiedad, SOAT, licencia de conducción y permiso para conducir interno | AX1: OBSERVACIONES | AY1: ¿Ha dormido al menos 7 horas en las últimas 24 horas? | AZ1: ¿Se encuentra libre de síntomas de fatiga (Somnolencia, dolor de cabeza, irritabilidad)? | BA1: ¿Se siente en condiciones físicas y mentales para conducir? | BB1: ¿Ha consumido medicamentos o sustancias que afecten su estado de alerta?
A2: 45853.492 | B2: Jin Ramírez | C2: MANTENIMIENTO (CONSORCIO SAS-CFP) | D2: DINA | E2: Ttto55 | F2: 104095 | G2: DIURNA | H2: CUMPLE | I2: CUMPLE | J2: CUMPLE | K2: CUMPLE | L2: CUMPLE | M2: CUMPLE | N2: CUMPLE | O2: CUMPLE | P2: CUMPLE | Q2: CUMPLE | R2: CUMPLE | S2: CUMPLE | T2: CUMPLE | U2: CUMPLE | V2: CUMPLE | W2: CUMPLE | X2: CUMPLE | Y2: CUMPLE | Z2: CUMPLE | AA2: CUMPLE | AB2: CUMPLE | AC2: CUMPLE | AD2: CUMPLE | AE2: CUMPLE | AF2: CUMPLE | AG2: CUMPLE | AH2: CUMPLE | AI2: CUMPLE | AJ2: CUMPLE | AK2: CUMPLE | AL2: CUMPLE | AM2: CUMPLE | AN2: CUMPLE | AO2: CUMPLE | AP2: CUMPLE | AQ2: CUMPLE | AR2: CUMPLE | AS2: CUMPLE | AT2: CUMPLE | AU2: CUMPLE | AV2: CUMPLE | AW2: CUMPLE | AX2: * se evidencia ruido en parte delantera, al equalizar el volante en zonas destapadas * Sistema de embrague se encuentra con fallas * Llantas delanteras están en mal estado * Vidrio lado pasajero, no baja | AY2: Cumple | AZ2: Cumple | BA2: Cumple | BB2: No
A3: 45853.672 | B3: Jorge Mosquera | C3: OPERACIÓN | D3: TELLO | E3: Ntq466 | F3: 5212 | G3: DIURNA | H3: CUMPLE | I3: CUMPLE | J3: CUMPLE | K3: CUMPLE | L3: CUMPLE | M3: CUMPLE | N3: CUMPLE | O3: CUMPLE | P3: CUMPLE | Q3: CUMPLE | R3: CUMPLE | S3: CUMPLE | T3: CUMPLE | U3: CUMPLE | V3: CUMPLE | W3: CUMPLE | X3: CUMPLE | Y3: CUMPLE | Z3: CUMPLE | AA3: CUMPLE | AB3: CUMPLE | AC3: CUMPLE | AD3: CUMPLE | AE3: CUMPLE | AF3: CUMPLE | AG3: CUMPLE | AH3: CUMPLE | AI3: CUMPLE | AJ3: CUMPLE | AK3: CUMPLE | AL3: CUMPLE | AM3: CUMPLE | AN3: CUMPLE | AO3: CUMPLE | AP3: CUMPLE | AQ3: CUMPLE | AR3: CUMPLE | AS3: CUMPLE | AT3: CUMPLE | AU3: CUMPLE | AV3: CUMPLE | AW3: CUMPLE | AY3: Cumple | AZ3: Cumple | BA3: Cumple | BB3: Si
A4: 45853.74 | B4: José Ramírez | C4: OPERACIÓN | D4: DINA | E4: THS596 | F4: 62196 | G4: NOCTURNA | H4: CUMPLE | I4: CUMPLE | J4: CUMPLE | K4: CUMPLE | L4: CUMPLE | M4: CUMPLE | N4: CUMPLE | O4: CUMPLE | P4: CUMPLE | Q4: CUMPLE | R4: CUMPLE | S4: CUMPLE | T4: CUMPLE | U4: CUMPLE | V4: CUMPLE | W4: CUMPLE | X4: CUMPLE | Y4: CUMPLE | Z4: CUMPLE | AA4: CUMPLE | AB4: CUMPLE | AC4: CUMPLE | AD4: CUMPLE | AE4: CUMPLE | AF4: CUMPLE | AG4: CUMPLE | AH4: CUMPLE | AI4: CUMPLE | AJ4: CUMPLE | AK4: CUMPLE | AL4: CUMPLE | AM4: CUMPLE | AN4: CUMPLE | AO4: CUMPLE | AP4: CUMPLE | AQ4: CUMPLE | AR4: CUMPLE | AS4: CUMPLE | AT4: CUMPLE | AU4: CUMPLE | AV4: CUMPLE | AW4: CUMPLE | AY4: Cumple | AZ4: Cumple | BA4: Cumple | BB4: No
A5: 45854.243 | B5: Alejandro aguja perez | C5: MANTENIMIENTO (CONSORCIO SAS-CFP) | D5: DINA | E5: Ths544 | F5: 42650 | G5: DIURNA | H5: CUMPLE | I5: CUMPLE | J5: CUMPLE | K5: CUMPLE | L5: CUMPLE | M5: CUMPLE | N5: CUMPLE | O5: CUMPLE | P5: CUMPLE | Q5: CUMPLE | R5: CUMPLE | S5: CUMPLE | T5: CUMPLE | U5: CUMPLE | V5: CUMPLE | W5: CUMPLE | X5: CUMPLE | Y5: CUMPLE | Z5: CUMPLE | AA5: CUMPLE | AB5: CUMPLE | AC5: NO APLICA | AD5: NO APLICA | AE5: NO APLICA | AF5: NO APLICA | AG5: CUMPLE | AH5: CUMPLE | AI5: CUMPLE | AJ5: CUMPLE | AK5: CUMPLE | AL5: CUMPLE | AM5: CUMPLE | AN5: CUMPLE | AO5: CUMPLE | AP5: CUMPLE | AQ5: CUMPLE | AR5: NO CUMPLE | AS5: CUMPLE | AT5: CUMPLE | AU5: CUMPLE | AV5: CUMPLE | AW5: CUMPLE | AX5: Sonido anormal en parte delantera | AY5: Cumple | AZ5: Cumple | BA5: Cumple | BB5: No
A6: 45854.27 | B6: Jhoan Tamayo Perdomo | C6: OPERACIÓN | D6: YAGUARA | E6: THS412 | F6: 37779 | G6: NO APLICA | H6: CUMPLE | I6: CUMPLE | J6: CUMPLE | K6: CUMPLE | L6: CUMPLE | M6: CUMPLE | N6: CUMPLE | O6: CUMPLE | P6: CUMPLE | Q6: NO CUMPLE | R6: CUMPLE | S6: CUMPLE | T6: CUMPLE | U6: CUMPLE | V6: CUMPLE | W6: CUMPLE | X6: CUMPLE | Y6: CUMPLE | Z6: CUMPLE | AA6: CUMPLE | AB6: CUMPLE | AC6: NO APLICA | AD6: NO APLICA | AE6: NO APLICA | AF6: NO APLICA | AG6: CUMPLE | AH6: CUMPLE | AI6: CUMPLE | AJ6: CUMPLE | AK6: CUMPLE | AL6: CUMPLE | AM6: CUMPLE | AN6: CUMPLE | AO6: CUMPLE | AP6: CUMPLE | AQ6: CUMPLE | AR6: CUMPLE | AS6: CUMPLE | AT6: CUMPLE | AU6: CUMPLE | AV6: CUMPLE | AW6: CUMPLE | AY6: Cumple | AZ6: Cumple | BA6: Cumple | BB6: No
A7: 45854.27 | B7: Gerardo ariza | C7: MANTENIMIENTO (CONSORCIO SAS-CFP) | D7: DINA | E7: EQZ742 | F7: 96703 | G7: DIURNA | H7: CUMPLE | I7: CUMPLE | J7: CUMPLE | K7: CUMPLE | L7: CUMPLE | M7: CUMPLE | N7: NO CUMPLE | O7: CUMPLE | P7: CUMPLE | Q7: CUMPLE | R7: CUMPLE | S7: CUMPLE | T7: CUMPLE | U7: CUMPLE | V7: CUMPLE | W7: CUMPLE | X7: CUMPLE | Y7: CUMPLE | Z7: CUMPLE | AA7: CUMPLE | AB7: CUMPLE | AC7: CUMPLE | AD7: CUMPLE | AE7: CUMPLE | AF7: NO APLICA | AG7: CUMPLE | AH7: CUMPLE | AI7: CUMPLE | AJ7: CUMPLE | AK7: CUMPLE | AL7: CUMPLE | AM7: CUMPLE | AN7: CUMPLE | AO7: CUMPLE | AP7: CUMPLE | AQ7: CUMPLE | AR7: CUMPLE | AS7: CUMPLE | AT7: CUMPLE | AU7: CUMPLE | AV7: CUMPLE | AW7: CUMPLE | AX7: Pendiente cambio panorámico, suministrar herramienta básicas, llantas traceras pequeñas, vías en mal estado, Pendiente cambio sensor de combustible, lavado general | AY7: Cumple | AZ7: Cumple | BA7: Cumple | BB7: No
A8: 45854.272 | B8: Juan Diego Cabrera | C8: OPERACIÓN | D8: SAN FRANCISCO | E8: THQ 021 | F8: 91550 | G8: DIURNA | H8: CUMPLE | I8: CUMPLE | J8: CUMPLE | K8: CUMPLE | L8: CUMPLE | M8: CUMPLE | N8: CUMPLE | O8: CUMPLE | P8: CUMPLE | Q8: CUMPLE | R8: CUMPLE | S8: CUMPLE | T8: CUMPLE | U8: CUMPLE | V8: CUMPLE | W8: CUMPLE | X8: CUMPLE | Y8: CUMPLE | Z8: CUMPLE | AA8: CUMPLE | AB8: CUMPLE | AC8: NO APLICA | AD8: NO APLICA | AE8: NO APLICA | AF8: NO APLICA | AG8: CUMPLE | AH8: CUMPLE | AI8: CUMPLE | AJ8: CUMPLE | AK8: CUMPLE | AL8: CUMPLE | AM8: CUMPLE | AN8: CUMPLE | AO8: CUMPLE | AP8: CUMPLE | AQ8: CUMPLE | AR8: CUMPLE | AS8: CUMPLE | AT8: CUMPLE | AU8: CUMPLE | AV8: CUMPLE | AW8: CUMPLE | AY8: Cumple | AZ8: Cumple | BA8: Cumple | BB8: No
A9: 45854.29 | B9: Betuel olarte dussan | C9: OPERACIÓN | D9: SAN FRANCISCO | E9: WPT277 | F9: 71115 | G9: DIURNA | H9: CUMPLE | I9: CUMPLE | J9: CUMPLE | K9: CUMPLE | L9: CUMPLE | M9: CUMPLE | N9: CUMPLE | O9: CUMPLE | P9: CUMPLE | Q9: CUMPLE | R9: CUMPLE | S9: CUMPLE | T9: CUMPLE | U9: CUMPLE | V9: CUMPLE | W9: CUMPLE | X9: CUMPLE | Y9: CUMPLE | Z9: CUMPLE | AA9: CUMPLE | AB9: CUMPLE | AC9: NO APLICA | AD9: NO APLICA | AE9: NO APLICA | AF9: NO APLICA | AG9: CUMPLE | AH9: CUMPLE | AI9: CUMPLE | AJ9: CUMPLE | AK9: CUMPLE | AL9: CUMPLE | AM9: CUMPLE | AN9: CUMPLE | AO9: CUMPLE | AP9: CUMPLE | AQ9: CUMPLE | AR9: CUMPLE | AS9: CUMPLE | AT9: CUMPLE | AU9: CUMPLE | AV9: CUMPLE | AW9: CUMPLE | AY9: Cumple | AZ9: Cumple | BA9: Cumple | BB9: No
A10: 45854.291 | B10: Arbey Trujillo Castro | C10: OPERACIÓN | D10: YAGUARA | E10: Loz104 | F10: 37121 | G10: DIURNA | H10: CUMPLE | I10: CUMPLE | J10: CUMPLE | K10: CUMPLE | L10: CUMPLE | M10: CUMPLE | N10: CUMPLE | O10: CUMPLE | P10: CUMPLE | Q10: NO CUMPLE | R10: CUMPLE | S10: CUMPLE | T10: CUMPLE | U10: NO CUMPLE | V10: CUMPLE | W10: CUMPLE | X10: CUMPLE | Y10: CUMPLE | Z10: CUMPLE | AA10: CUMPLE | AB10: CUMPLE | AC10: CUMPLE | AD10: CUMPLE | AE10: CUMPLE | AF10: CUMPLE | AG10: CUMPLE | AH10: CUMPLE | AI10: CUMPLE | AJ10: CUMPLE | AK10: CUMPLE | AL10: CUMPLE | AM10: CUMPLE | AN10: CUMPLE | AO10: CUMPLE | AP10: CUMPLE | AQ10: CUMPLE | AR10: CUMPLE | AS10: CUMPLE | AT10: CUMPLE | AU10: CUMPLE | AV10: CUMPLE | AW10: CUMPLE | AY10: Cumple | AZ10: Cumple | BA10: Cumple | BB10: No
A11: 45854.3 | B11: Sergio Barreto | C11: OPERACIÓN | D11: TELLO | E11: THS658 | F11: 851 | G11: DIURNA | H11: CUMPLE | I11: CUMPLE | J11: CUMPLE | K11: CUMPLE | L11: CUMPLE | M11: CUMPLE | N11: CUMPLE | O11: CUMPLE | P11: CUMPLE | Q11: CUMPLE | R11: CUMPLE | S11: CUMPLE | T11: CUMPLE | U11: CUMPLE | V11: CUMPLE | W11: CUMPLE | X11: CUMPLE | Y11: CUMPLE | Z11: CUMPLE | AA11: CUMPLE | AB11: CUMPLE | AC11: NO APLICA | AD11: NO APLICA | AE11: NO APLICA | AF11: NO APLICA | AG11: CUMPLE | AH11: CUMPLE | AI11: CUMPLE | AJ11: CUMPLE | AK11: CUMPLE | AL11: CUMPLE | AM11: CUMPLE | AN11: CUMPLE | AO11: CUMPLE | AP11: CUMPLE | AQ11: CUMPLE | AR11: CUMPLE | AS11: CUMPLE | AT11: CUMPLE | AU11: CUMPLE | AV11: CUMPLE | AW11: CUMPLE | AY11: Cumple | AZ11: Cumple | BA11: Cumple | BB11: No
A12: 45854.306 | B12: Aldemar González Lasso | C12: MANTENIMIENTO (CONSORCIO SAS-CFP) | D12: SAN FRANCISCO | E12: THS530 | F12: 55412 | G12: DIURNA | H12: CUMPLE | I12: CUMPLE | J12: CUMPLE | K12: CUMPLE | L12: CUMPLE | M12: CUMPLE | N12: CUMPLE | O12: CUMPLE | P12: CUMPLE | Q12: CUMPLE | R12: CUMPLE | S12: CUMPLE | T12: CUMPLE | U12: CUMPLE | V12: CUMPLE | W12: CUMPLE | X12: CUMPLE | Y12: CUMPLE | Z12: CUMPLE | AA12: CUMPLE | AB12: CUMPLE | AC12: NO APLICA | AD12: NO APLICA | AE12: NO APLICA | AF12: NO APLICA | AG12: CUMPLE | AH12: CUMPLE | AI12: CUMPLE | AJ12: CUMPLE | AK12: CUMPLE | AL12: CUMPLE | AM12: CUMPLE | AN12: CUMPLE | AO12: CUMPLE | AP12: CUMPLE | AQ12: CUMPLE | AR12: CUMPLE | AS12: CUMPLE | AT12: CUMPLE | AU12: CUMPLE | AV12: CUMPLE | AW12: CUMPLE | AX12: Sin novedad | AY12: Cumple | AZ12: Cumple | BA12: Cumple | BB12: No
A13: 45854.312 | B13: YILBER LOSADA | C13: OPERACIÓN | D13: DINA | E13: WPT278 | F13: 137317 | G13: DIURNA | H13: CUMPLE | I13: CUMPLE | J13: CUMPLE | K13: CUMPLE | L13: CUMPLE | M13: CUMPLE | N13: CUMPLE | O13: CUMPLE | P13: NO CUMPLE | Q13: CUMPLE | R13: CUMPLE | S13: CUMPLE | T13: CUMPLE | U13: CUMPLE | V13: CUMPLE | W13: CUMPLE | X13: CUMPLE | Y13: CUMPLE | Z13: CUMPLE | AA13: CUMPLE | AB13: CUMPLE | AC13: NO APLICA | AD13: NO APLICA | AE13: NO APLICA | AF13: NO APLICA | AG13: CUMPLE | AH13: CUMPLE | AI13: CUMPLE | AJ13: CUMPLE | AK13: CUMPLE | AL13: CUMPLE | AM13: CUMPLE | AN13: CUMPLE | AO13: CUMPLE | AP13: CUMPLE | AQ13: CUMPLE | AR13: CUMPLE | AS13: CUMPLE | AT13: CUMPLE | AU13: CUMPLE | AV13: CUMPLE | AW13: CUMPLE | AX13: Realizar cambio de.aceite Actual 137317 PRO 136913 | AY13: Cumple | AZ13: Cumple | BA13: Cumple | BB13: No
A14: 45854.347 | B14: Leonardo charry charry | C14: OPERACIÓN | D14: DINA | E14: WPT-247 | F14: 106733 | G14: DIURNA | H14: CUMPLE | I14: CUMPLE | J14: CUMPLE | K14: CUMPLE | L14: CUMPLE | M14: CUMPLE | N14: CUMPLE | O14: CUMPLE | P14: CUMPLE | Q14: CUMPLE | R14: CUMPLE | S14: CUMPLE | T14: CUMPLE | U14: CUMPLE | V14: CUMPLE | W14: CUMPLE | X14: CUMPLE | Y14: CUMPLE | Z14: CUMPLE | AA14: CUMPLE | AB14: CUMPLE | AC14: NO APLICA | AD14: NO APLICA | AE14: NO APLICA | AF14: NO APLICA | AG14: CUMPLE | AH14: CUMPLE | AI14: CUMPLE | AJ14: CUMPLE | AK14: CUMPLE | AL14: CUMPLE | AM14: CUMPLE | AN14: CUMPLE | AO14: CUMPLE | AP14: CUMPLE | AQ14: CUMPLE | AR14: CUMPLE | AS14: CUMPLE | AT14: CUMPLE | AU14: CUMPLE | AV14: CUMPLE | AW14: CUMPLE | AX14: La manija de la puerta de izquierda está dañada, el líquido de limpia parabrisas no esa funcionando el filtro está Dañado | AY14: Cumple | AZ14: Cumple | BA14: Cumple | BB14: Si
A15: 45854.365 | B15: DEYMER BORRERO MOSQUERA | C15: OPERACIÓN | D15: TELLO | E15: WPT241 | F15: 60502 | G15: DIURNA | H15: CUMPLE | I15: CUMPLE | J15: CUMPLE | K15: CUMPLE | L15: CUMPLE | M15: CUMPLE | N15: CUMPLE | O15: CUMPLE | P15: CUMPLE | Q15: CUMPLE | R15: CUMPLE | S15: CUMPLE | T15: CUMPLE | U15: CUMPLE | V15: CUMPLE | W15: CUMPLE | X15: CUMPLE | Y15: CUMPLE | Z15: CUMPLE | AA15: CUMPLE | AB15: CUMPLE | AC15: NO APLICA | AD15: NO APLICA | AE15: NO APLICA | AF15: NO APLICA | AG15: CUMPLE | AH15: CUMPLE | AI15: CUMPLE | AJ15: CUMPLE | AK15: CUMPLE | AL15: CUMPLE | AM15: CUMPLE | AN15: CUMPLE | AO15: CUMPLE | AP15: CUMPLE | AQ15: CUMPLE | AR15: CUMPLE | AS15: CUMPLE | AT15: CUMPLE | AU15: CUMPLE | AV15: CUMPLE | AW15: CUMPLE | AY15: Cumple | AZ15: Cumple | BA15: Cumple | BB15: No
A16: 45854.396 | B16: Miller Jesús charry | C16: OPERACIÓN | D16: SAN FRANCISCO | E16: Wpt -245 | F16: 11017 | G16: DIURNA | H16: CUMPLE | I16: CUMPLE | J16: CUMPLE | K16: CUMPLE | L16: CUMPLE | M16: NO CUMPLE | N16: CUMPLE | O16: CUMPLE | P16: CUMPLE | Q16: CUMPLE | R16: CUMPLE | S16: CUMPLE | T16: CUMPLE | U16: CUMPLE | V16: CUMPLE | W16: CUMPLE | X16: CUMPLE | Y16: CUMPLE | Z16: CUMPLE | AA16: CUMPLE | AB16: CUMPLE | AC16: NO APLICA | AD16: NO APLICA | AE16: NO APLICA | AF16: NO APLICA | AG16: CUMPLE | AH16: CUMPLE | AI16: CUMPLE | AJ16: CUMPLE | AK16: CUMPLE | AL16: CUMPLE | AM16: CUMPLE | AN16: CUMPLE | AO16: CUMPLE | AP16: CUMPLE | AQ16: CUMPLE | AR16: CUMPLE | AS16: CUMPLE | AT16: CUMPLE | AU16: CUMPLE | AV16: CUMPLE | AW16: CUMPLE | AX16: Ninguna | AY16: Cumple | AZ16: Cumple | BA16: Cumple | BB16: No
A17: 45854.666 | B17: Jonh edinsson Charry Villarreal | C17: OPERACIÓN | D17: DINA | E17: THQ-137 | F17: 83810 | G17: DIURNA | H17: CUMPLE | I17: CUMPLE | J17: CUMPLE | K17: CUMPLE | L17: CUMPLE | M17: CUMPLE | N17: CUMPLE | O17: CUMPLE | P17: CUMPLE | Q17: CUMPLE | R17: CUMPLE | S17: CUMPLE | T17: CUMPLE | U17: CUMPLE | V17: CUMPLE | W17: CUMPLE | X17: NO CUMPLE | Y17: CUMPLE | Z17: CUMPLE | AA17: CUMPLE | AB17: CUMPLE | AC17: NO APLICA | AD17: NO APLICA | AE17: NO APLICA | AF17: NO APLICA | AG17: CUMPLE | AH17: CUMPLE | AI17: CUMPLE | AJ17: CUMPLE | AK17: CUMPLE | AL17: CUMPLE | AM17: CUMPLE | AN17: CUMPLE | AO17: NO CUMPLE | AP17: NO CUMPLE | AQ17: CUMPLE | AR17: CUMPLE | AS17: CUMPLE | AT17: CUMPLE | AU17: CUMPLE | AV17: CUMPLE | AW17: CUMPLE | AY17: Cumple | AZ17: Cumple | BA17: Cumple | BB17: No
A18: 45854.741 | B18: José Ramírez | C18: OPERACIÓN | D18: DINA | E18: EQQ647 | F18: 220724 | G18: NOCTURNA | H18: CUMPLE | I18: CUMPLE | J18: CUMPLE | K18: CUMPLE | L18: CUMPLE | M18: CUMPLE | N18: CUMPLE | O18: CUMPLE | P18: CUMPLE | Q18: CUMPLE | R18: CUMPLE | S18: CUMPLE | T18: CUMPLE | U18: CUMPLE | V18: CUMPLE | W18: CUMPLE | X18: CUMPLE | Y18: CUMPLE | Z18: CUMPLE | AA18: CUMPLE | AB18: CUMPLE | AC18: CUMPLE | AD18: CUMPLE | AE18: CUMPLE | AF18: CUMPLE | AG18: CUMPLE | AH18: CUMPLE | AI18: CUMPLE | AJ18: CUMPLE | AK18: CUMPLE | AL18: CUMPLE | AM18: CUMPLE | AN18: CUMPLE | AO18: CUMPLE | AP18: CUMPLE | AQ18: CUMPLE | AR18: CUMPLE | AS18: CUMPLE | AT18: CUMPLE | AU18: CUMPLE | AV18: CUMPLE | AW18: CUMPLE | AY18: Cumple | AZ18: Cumple | BA18: Cumple | BB18: No
A19: 45855.27 | B19: DEYMER BORRERO MOSQUERA | C19: OPERACIÓN | D19: TELLO | E19: WPT241 | F19: 60574 | G19: DIURNA | H19: CUMPLE | I19: CUMPLE | J19: CUMPLE | K19: CUMPLE | L19: CUMPLE | M19: CUMPLE | N19: CUMPLE | O19: CUMPLE | P19: CUMPLE | Q19: CUMPLE | R19: CUMPLE | S19: CUMPLE | T19: CUMPLE | U19: CUMPLE | V19: CUMPLE | W19: CUMPLE | X19: CUMPLE | Y19: CUMPLE | Z19: CUMPLE | AA19: CUMPLE | AB19: CUMPLE | AC19: NO APLICA | AD19: NO APLICA | AE19: NO APLICA | AF19: NO APLICA | AG19: CUMPLE | AH19: CUMPLE | AI19: CUMPLE | AJ19: CUMPLE | AK19: CUMPLE | AL19: CUMPLE | AM19: CUMPLE | AN19: CUMPLE | AO19: CUMPLE | AP19: CUMPLE | AQ19: CUMPLE | AR19: CUMPLE | AS19: CUMPLE | AT19: CUMPLE | AU19: CUMPLE | AV19: CUMPLE | AW19: CUMPLE | AY19: Cumple | AZ19: Cumple | BA19: Cumple | BB19: No
A20: 45855.27 | B20: Jhoan Tamayo Perdomo | C20: OPERACIÓN | D20: YAGUARA | E20: THS412 | F20: 37809 | G20: NO APLICA | H20: CUMPLE | I20: CUMPLE | J20: CUMPLE | K20: CUMPLE | L20: CUMPLE | M20: CUMPLE | N20: CUMPLE | O20: CUMPLE | P20: CUMPLE | Q20: NO CUMPLE | R20: CUMPLE | S20: CUMPLE | T20: CUMPLE | U20: CUMPLE | V20: CUMPLE | W20: CUMPLE | X20: CUMPLE | Y20: CUMPLE | Z20: CUMPLE | AA20: CUMPLE | AB20: CUMPLE | AC20: NO APLICA | AD20: NO APLICA | AE20: NO APLICA | AF20: NO APLICA | AG20: CUMPLE | AH20: CUMPLE | AI20: CUMPLE | AJ20: CUMPLE | AK20: CUMPLE | AL20: CUMPLE | AM20: CUMPLE | AN20: CUMPLE | AO20: CUMPLE | AP20: CUMPLE | AQ20: CUMPLE | AR20: CUMPLE | AS20: CUMPLE | AT20: CUMPLE | AU20: CUMPLE | AV20: CUMPLE | AW20: CUMPLE | AY20: Cumple | AZ20: Cumple | BA20: Cumple | BB20: No
A21: 45855.272 | B21: Arbey trujillo | C21: MANTENIMIENTO (CONSORCIO SAS-CFP) | D21: YAGUARA | E21: LPZ104 | F21: 37165 | G21: DIURNA | H21: CUMPLE | I21: CUMPLE | J21: CUMPLE | K21: CUMPLE | L21: CUMPLE | M21: CUMPLE | N21: CUMPLE | O21: CUMPLE | P21: CUMPLE | Q21: CUMPLE | R21: CUMPLE | S21: CUMPLE | T21: CUMPLE | U21: NO CUMPLE | V21: CUMPLE | W21: CUMPLE | X21: CUMPLE | Y21: CUMPLE | Z21: CUMPLE | AA21: CUMPLE | AB21: CUMPLE | AC21: CUMPLE | AD21: CUMPLE | AE21: CUMPLE | AF21: CUMPLE | AG21: CUMPLE | AH21: CUMPLE | AI21: CUMPLE | AJ21: CUMPLE | AK21: CUMPLE | AL21: CUMPLE | AM21: CUMPLE | AN21: CUMPLE | AO21: CUMPLE | AP21: CUMPLE | AQ21: CUMPLE | AR21: CUMPLE | AS21: CUMPLE | AT21: CUMPLE | AU21: CUMPLE | AV21: CUMPLE | AW21: CUMPLE | AY21: Cumple | AZ21: Cumple | BA21: Cumple | BB21: No
A22: 45855.286 | B22: Michelle Aroca Medina | C22: OPERACIÓN | D22: SAN FRANCISCO | E22: WPT 243 | F22: 95892 | G22: DIURNA | H22: CUMPLE | I22: CUMPLE | J22: CUMPLE | K22: CUMPLE | L22: CUMPLE | M22: CUMPLE | N22: CUMPLE | O22: CUMPLE | P22: CUMPLE | Q22: CUMPLE | R22: CUMPLE | S22: CUMPLE | T22: CUMPLE | U22: CUMPLE | V22: CUMPLE | W22: CUMPLE | X22: CUMPLE | Y22: CUMPLE | Z22: CUMPLE | AA22: CUMPLE | AB22: CUMPLE | AC22: NO APLICA | AD22: NO APLICA | AE22: NO APLICA | AF22: NO APLICA | AG22: CUMPLE | AH22: CUMPLE | AI22: CUMPLE | AJ22: CUMPLE | AK22: CUMPLE | AL22: CUMPLE | AM22: CUMPLE | AN22: CUMPLE | AO22: CUMPLE | AP22: CUMPLE | AQ22: CUMPLE | AR22: CUMPLE | AS22: CUMPLE | AT22: CUMPLE | AU22: CUMPLE | AV22: CUMPLE | AW22: CUMPLE | AX22: Hay que bajar el carro para hacer unos ajustes | AY22: Cumple | AZ22: Cumple | BA22: Cumple | BB22: No
A23: 45855.291 | B23: YILBER LOSADA | C23: OPERACIÓN | D23: DINA | E23: WPT278 | F23: 137379 | G23: DIURNA | H23: CUMPLE | I23: CUMPLE | J23: CUMPLE | K23: CUMPLE | L23: CUMPLE | M23: CUMPLE | N23: CUMPLE | O23: CUMPLE | P23: CUMPLE | Q23: CUMPLE | R23: CUMPLE | S23: CUMPLE | T23: CUMPLE | U23: CUMPLE | V23: CUMPLE | W23: CUMPLE | X23: CUMPLE | Y23: CUMPLE | Z23: CUMPLE | AA23: CUMPLE | AB23: CUMPLE | AC23: NO APLICA | AD23: NO APLICA | AE23: NO APLICA | AF23: NO APLICA | AG23: CUMPLE | AH23: CUMPLE | AI23: CUMPLE | AJ23: CUMPLE | AK23: CUMPLE | AL23: CUMPLE | AM23: NO CUMPLE | AN23: CUMPLE | AO23: CUMPLE | AP23: CUMPLE | AQ23: CUMPLE | AR23: CUMPLE | AS23: CUMPLE | AT23: CUMPLE | AU23: CUMPLE | AV23: CUMPLE | AW23: CUMPLE | AX23: Cambionde.aceite Actual 137379 Prox 136913 | AY23: Cumple | AZ23: Cumple | BA23: Cumple | BB23: No
A24: 45855.308 | B24: Sergio Barreto | C24: OPERACIÓN | D24: TELLO | E24: THS658 | F24: 795 | G24: DIURNA | H24: CUMPLE | I24: CUMPLE | J24: CUMPLE | K24: CUMPLE | L24: CUMPLE | M24: CUMPLE | N24: CUMPLE | O24: CUMPLE | P24: CUMPLE | Q24: CUMPLE | R24: CUMPLE | S24: CUMPLE | T24: CUMPLE | U24: CUMPLE | V24: CUMPLE | W24: CUMPLE | X24: CUMPLE | Y24: CUMPLE | Z24: CUMPLE | AA24: CUMPLE | AB24: CUMPLE | AC24: NO APLICA | AD24: NO APLICA | AE24: NO APLICA | AF24: NO APLICA | AG24: CUMPLE | AH24: CUMPLE | AI24: CUMPLE | AJ24: CUMPLE | AK24: CUMPLE | AL24: CUMPLE | AM24: CUMPLE | AN24: CUMPLE | AO24: CUMPLE | AP24: CUMPLE | AQ24: CUMPLE | AR24: CUMPLE | AS24: CUMPLE | AT24: CUMPLE | AU24: CUMPLE | AV24: CUMPLE | AW24: CUMPLE | AY24: Cumple | AZ24: Cumple | BA24: Cumple | BB24: No
A25: 45855.311 | B25: Aldemar González Lasso | C25: MANTENIMIENTO (CONSORCIO SAS-CFP) | D25: SAN FRANCISCO | E25: THS530 | F25: 55456 | G25: DIURNA | H25: CUMPLE | I25: CUMPLE | J25: CUMPLE | K25: CUMPLE | L25: CUMPLE | M25: CUMPLE | N25: CUMPLE | O25: CUMPLE | P25: CUMPLE | Q25: CUMPLE | R25: CUMPLE | S25: CUMPLE | T25: CUMPLE | U25: CUMPLE | V25: CUMPLE | W25: CUMPLE | X25: CUMPLE | Y25: CUMPLE | Z25: CUMPLE | AA25: CUMPLE | AB25: CUMPLE | AC25: NO APLICA | AD25: NO APLICA | AE25: NO APLICA | AF25: NO APLICA | AG25: CUMPLE | AH25: CUMPLE | AI25: CUMPLE | AJ25: CUMPLE | AK25: CUMPLE | AL25: CUMPLE | AM25: CUMPLE | AN25: CUMPLE | AO25: CUMPLE | AP25: CUMPLE | AQ25: CUMPLE | AR25: CUMPLE | AS25: CUMPLE | AT25: CUMPLE | AU25: CUMPLE | AV25: CUMPLE | AW25: CUMPLE | AX25: Sin novedad | AY25: Cumple | AZ25: Cumple | BA25: Cumple | BB25: No
A26: 45855.314 | B26: Rubén cubillos | C26: MANTENIMIENTO (CONSORCIO SAS-CFP) | D26: DINA | E26: THP849 | F26: 130306 | G26: DIURNA | H26: CUMPLE | I26: CUMPLE | J26: CUMPLE | K26: CUMPLE | L26: CUMPLE | M26: CUMPLE | N26: CUMPLE | O26: CUMPLE | P26: CUMPLE | Q26: CUMPLE | R26: CUMPLE | S26: CUMPLE | T26: CUMPLE | U26: CUMPLE | V26: CUMPLE | W26: CUMPLE | X26: CUMPLE | Y26: CUMPLE | Z26: CUMPLE | AA26: CUMPLE | AB26: CUMPLE | AC26: NO APLICA | AD26: NO APLICA | AE26: NO APLICA | AF26: NO APLICA | AG26: CUMPLE | AH26: CUMPLE | AI26: CUMPLE | AJ26: CUMPLE | AK26: CUMPLE | AL26: CUMPLE | AM26: CUMPLE | AN26: CUMPLE | AO26: CUMPLE | AP26: CUMPLE | AQ26: CUMPLE | AR26: CUMPLE | AS26: CUMPLE | AT26: CUMPLE | AU26: CUMPLE | AV26: CUMPLE | AW26: CUMPLE | AY26: Cumple | AZ26: Cumple | BA26: Cumple | BB26: No
A27: 45855.317 | B27: Jonh edinsson Charry Villarreal | C27: OPERACIÓN | D27: DINA | E27: THQ-137 | F27: 83850 | G27: DIURNA | H27: CUMPLE | I27: CUMPLE | J27: CUMPLE | K27: CUMPLE | L27: CUMPLE | M27: CUMPLE | N27: CUMPLE | O27: CUMPLE | P27: CUMPLE | Q27: CUMPLE | R27: CUMPLE | S27: CUMPLE | T27: CUMPLE | U27: CUMPLE | V27: CUMPLE | W27: CUMPLE | X27: NO CUMPLE | Y27: CUMPLE | Z27: CUMPLE | AA27: CUMPLE | AB27: CUMPLE | AC27: NO APLICA | AD27: NO APLICA | AE27: NO APLICA | AF27: NO APLICA | AG27: CUMPLE | AH27: CUMPLE | AI27: CUMPLE | AJ27: CUMPLE | AK27: CUMPLE | AL27: CUMPLE | AM27: CUMPLE | AN27: CUMPLE | AO27: NO CUMPLE | AP27: NO CUMPLE | AQ27: CUMPLE | AR27: CUMPLE | AS27: CUMPLE | AT27: CUMPLE | AU27: CUMPLE | AV27: CUMPLE | AW27: CUMPLE | AY27: Cumple | AZ27: Cumple | BA27: Cumple | BB27: No
A28: 45855.317 | B28: Jorge Lasso diaz | C28: OPERACIÓN | D28: DINA | E28: THQ 136 | F28: 71395 | G28: DIURNA | H28: CUMPLE | I28: CUMPLE | J28: CUMPLE | K28: CUMPLE | L28: CUMPLE | M28: CUMPLE | N28: CUMPLE | O28: CUMPLE | P28: CUMPLE | Q28: CUMPLE | R28: CUMPLE | S28: CUMPLE | T28: CUMPLE | U28: CUMPLE | V28: CUMPLE | W28: CUMPLE | X28: CUMPLE | Y28: CUMPLE | Z28: CUMPLE | AA28: CUMPLE | AB28: CUMPLE | AC28: NO APLICA | AD28: NO APLICA | AE28: NO APLICA | AF28: NO APLICA | AG28: CUMPLE | AH28: CUMPLE | AI28: CUMPLE | AJ28: CUMPLE | AK28: CUMPLE | AL28: CUMPLE | AM28: CUMPLE | AN28: CUMPLE | AO28: CUMPLE | AP28: CUMPLE | AQ28: CUMPLE | AR28: CUMPLE | AS28: CUMPLE | AT28: CUMPLE | AU28: CUMPLE | AV28: CUMPLE | AW28: CUMPLE | AY28: Cumple | AZ28: Cumple | BA28: No cumple | BB28: No
A29: 45855.32 | B29: Wilver Collazos Quiroga | C29: MANTENIMIENTO (CONSORCIO SAS-CFP) | D29: DINA | E29: WPT 239 | F29: 104212 | G29: DIURNA | H29: CUMPLE | I29: CUMPLE | J29: CUMPLE | K29: CUMPLE | L29: CUMPLE | M29: CUMPLE | N29: CUMPLE | O29: CUMPLE | P29: CUMPLE | Q29: CUMPLE | R29: CUMPLE | S29: CUMPLE | T29: CUMPLE | U29: CUMPLE | V29: CUMPLE | W29: CUMPLE | X29: CUMPLE | Y29: CUMPLE | Z29: CUMPLE | AA29: CUMPLE | AB29: CUMPLE | AC29: NO APLICA | AD29: NO APLICA | AE29: NO APLICA | AF29: NO APLICA | AG29: CUMPLE | AH29: CUMPLE | AI29: CUMPLE | AJ29: CUMPLE | AK29: CUMPLE | AL29: CUMPLE | AM29: CUMPLE | AN29: CUMPLE | AO29: CUMPLE | AP29: CUMPLE | AQ29: CUMPLE | AR29: CUMPLE | AS29: CUMPLE | AT29: CUMPLE | AU29: CUMPLE | AV29: CUMPLE | AW29: CUMPLE | AX29: Parabrisas fisurado, se requiere cambio de tuercas de llantas delnteras, rayones leves en cabina por maleza hacía las vías de algunos pozos, el vehículo se le está filtrando el agua lluvia por el vidrio trasero, vías en mal estado y pueden causar daños a partes del vehículo, unidad lateral izquierdo fisurada ya hace más de dos años | AY29: Cumple | AZ29: Cumple | BA29: Cumple | BB29: No
A30: 45855.348 | B30: Javier Alfonso Amaya Suárez | C30: MANTENIMIENTO (CONSORCIO SAS-CFP) | D30: DINA | E30: WPT354 | F30: 123015 | G30: DIURNA | H30: CUMPLE | I30: CUMPLE | J30: CUMPLE | K30: CUMPLE | L30: CUMPLE | M30: CUMPLE | N30: CUMPLE | O30: CUMPLE | P30: CUMPLE | Q30: CUMPLE | R30: CUMPLE | S30: CUMPLE | T30: CUMPLE | U30: CUMPLE | V30: CUMPLE | W30: CUMPLE | X30: CUMPLE | Y30: CUMPLE | Z30: CUMPLE | AA30: CUMPLE | AB30: CUMPLE | AC30: NO APLICA | AD30: NO APLICA | AE30: NO APLICA | AF30: NO APLICA | AG30: CUMPLE | AH30: CUMPLE | AI30: CUMPLE | AJ30: CUMPLE | AK30: CUMPLE | AL30: CUMPLE | AM30: CUMPLE | AN30: CUMPLE | AO30: CUMPLE | AP30: CUMPLE | AQ30: CUMPLE | AR30: CUMPLE | AS30: CUMPLE | AT30: CUMPLE | AU30: CUMPLE | AV30: CUMPLE | AW30: CUMPLE | AX30: Presenta ruido en la correa de accesorios, la silla del copiloto se unde, las llantas traceras están desgastadas, la manija del lado derecho puerta tracera dañada por cristalización de material | AY30: Cumple | AZ30: Cumple | BA30: Cumple | BB30: No
A31: 45855.364 | B31: Leonardo charry charry | C31: OPERACIÓN | D31: DINA | E31: WPT247 | F31: 106742 | G31: DIURNA | H31: CUMPLE | I31: CUMPLE | J31: CUMPLE | K31: CUMPLE | L31: CUMPLE | M31: CUMPLE | N31: CUMPLE | O31: CUMPLE | P31: CUMPLE | Q31: CUMPLE | R31: CUMPLE | S31: CUMPLE | T31: CUMPLE | U31: CUMPLE | V31: CUMPLE | W31: CUMPLE | X31: CUMPLE | Y31: CUMPLE | Z31: CUMPLE | AA31: CUMPLE | AB31: CUMPLE | AC31: NO APLICA | AD31: NO APLICA | AE31: NO APLICA | AF31: NO APLICA | AG31: CUMPLE | AH31: CUMPLE | AI31: CUMPLE | AJ31: CUMPLE | AK31: CUMPLE | AL31: CUMPLE | AM31: CUMPLE | AN31: CUMPLE | AO31: CUMPLE | AP31: CUMPLE | AQ31: CUMPLE | AR31: CUMPLE | AS31: CUMPLE | AT31: CUMPLE | AU31: CUMPLE | AV31: CUMPLE | AW31: CUMPLE | AX31: La manija , del puerta izquierda está dañada, el filtro de agua del limpia vidrio | AY31: Cumple | AZ31: Cumple | BA31: Cumple | BB31: No
A32: 45855.422 | B32: Betuel olarte dussan | C32: OPERACIÓN | D32: SAN FRANCISCO | E32: WPT277 | F32: 71138 | G32: DIURNA | H32: CUMPLE | I32: CUMPLE | J32: CUMPLE | K32: CUMPLE | L32: CUMPLE | M32: CUMPLE | N32: CUMPLE | O32: CUMPLE | P32: CUMPLE | Q32: CUMPLE | R32: CUMPLE | S32: CUMPLE | T32: CUMPLE | U32: CUMPLE | V32: CUMPLE | W32: CUMPLE | X32: CUMPLE | Y32: CUMPLE | Z32: CUMPLE | AA32: CUMPLE | AB32: CUMPLE | AC32: NO APLICA | AD32: NO APLICA | AE32: NO APLICA | AF32: NO APLICA | AG32: CUMPLE | AH32: CUMPLE | AI32: CUMPLE | AJ32: CUMPLE | AK32: CUMPLE | AL32: CUMPLE | AM32: CUMPLE | AN32: CUMPLE | AO32: CUMPLE | AP32: CUMPLE | AQ32: CUMPLE | AR32: CUMPLE | AS32: CUMPLE | AT32: CUMPLE | AU32: CUMPLE | AV32: CUMPLE | AW32: CUMPLE | AY32: Cumple | AZ32: Cumple | BA32: Cumple | BB32: No
A33: 45855.625 | B33: Capitolino mateus | C33: MANTENIMIENTO (CONSORCIO SAS-CFP) | D33: DINA | E33: Eqz286 | F33: 944975 | G33: DIURNA | H33: CUMPLE | I33: CUMPLE | J33: CUMPLE | K33: CUMPLE | L33: CUMPLE | M33: CUMPLE | N33: CUMPLE | O33: CUMPLE | P33: CUMPLE | Q33: CUMPLE | R33: CUMPLE | S33: CUMPLE | T33: CUMPLE | U33: CUMPLE | V33: CUMPLE | W33: CUMPLE | X33: CUMPLE | Y33: CUMPLE | Z33: CUMPLE | AA33: CUMPLE | AB33: CUMPLE | AC33: NO APLICA | AD33: NO APLICA | AE33: NO APLICA | AF33: NO APLICA | AG33: CUMPLE | AH33: CUMPLE | AI33: CUMPLE | AJ33: CUMPLE | AK33: CUMPLE | AL33: CUMPLE | AM33: CUMPLE | AN33: CUMPLE | AO33: CUMPLE | AP33: CUMPLE | AQ33: CUMPLE | AR33: CUMPLE | AS33: CUMPLE | AT33: CUMPLE | AU33: CUMPLE | AV33: CUMPLE | AW33: CUMPLE | AX33: Todo bien | AY33: Cumple | AZ33: Cumple | BA33: Cumple | BB33: No
A34: 45855.628 | B34: Gerardo ariza | C34: MANTENIMIENTO (CONSORCIO SAS-CFP) | D34: DINA | E34: EQZ742 | F34: 65500 | G34: DIURNA | H34: CUMPLE | I34: CUMPLE | J34: CUMPLE | K34: CUMPLE | L34: CUMPLE | M34: CUMPLE | N34: NO CUMPLE | O34: CUMPLE | P34: CUMPLE | Q34: CUMPLE | R34: CUMPLE | S34: CUMPLE | T34: CUMPLE | U34: CUMPLE | V34: CUMPLE | W34: CUMPLE | X34: CUMPLE | Y34: CUMPLE | Z34: CUMPLE | AA34: CUMPLE | AB34: CUMPLE | AC34: CUMPLE | AD34: CUMPLE | AE34: CUMPLE | AF34: NO APLICA | AG34: CUMPLE | AH34: CUMPLE | AI34: CUMPLE | AJ34: CUMPLE | AK34: CUMPLE | AL34: CUMPLE | AM34: CUMPLE | AN34: CUMPLE | AO34: CUMPLE | AP34: CUMPLE | AQ34: CUMPLE | AR34: CUMPLE | AS34: CUMPLE | AT34: CUMPLE | AU34: CUMPLE | AV34: CUMPLE | AW34: CUMPLE | AX34: Pendiente cambio panorámico, suministrar herramienta básicas, llantas traceras pequeñas, vías en mal estado, Pendiente cambio sensor de combustible, lavado general, cambio de.luces laterales,soldadura de.canasta | AY34: Cumple | AZ34: Cumple | BA34: Cumple | BB34: No
A35: 45855.727 | B35: José Ramírez | C35: OPERACIÓN | D35: DINA | E35: EQQ657 | F35: 220818 | G35: NOCTURNA | H35: CUMPLE | I35: CUMPLE | J35: CUMPLE | K35: CUMPLE | L35: CUMPLE | M35: CUMPLE | N35: CUMPLE | O35: CUMPLE | P35: CUMPLE | Q35: CUMPLE | R35: CUMPLE | S35: CUMPLE | T35: CUMPLE | U35: CUMPLE | V35: CUMPLE | W35: CUMPLE | X35: CUMPLE | Y35: CUMPLE | Z35: CUMPLE | AA35: CUMPLE | AB35: CUMPLE | AC35: CUMPLE | AD35: CUMPLE | AE35: CUMPLE | AF35: CUMPLE | AG35: CUMPLE | AH35: CUMPLE | AI35: CUMPLE | AJ35: CUMPLE | AK35: CUMPLE | AL35: CUMPLE | AM35: CUMPLE | AN35: CUMPLE | AO35: CUMPLE | AP35: CUMPLE | AQ35: CUMPLE | AR35: CUMPLE | AS35: CUMPLE | AT35: CUMPLE | AU35: CUMPLE | AV35: CUMPLE | AW35: CUMPLE | AY35: Cumple | AZ35: Cumple | BA35: Cumple | BB35: No
A36: 45856.215 | B36: Jose Miller Escobar Tello | C36: OPERACIÓN | D36: TELLO | E36: Lhw. 521 | F36: 86257 | G36: DIURNA | H36: CUMPLE | I36: CUMPLE | J36: CUMPLE | K36: CUMPLE | L36: CUMPLE | M36: CUMPLE | N36: CUMPLE | O36: CUMPLE | P36: CUMPLE | Q36: CUMPLE | R36: CUMPLE | S36: CUMPLE | T36: CUMPLE | U36: CUMPLE | V36: CUMPLE | W36: CUMPLE | X36: CUMPLE | Y36: CUMPLE | Z36: CUMPLE | AA36: CUMPLE | AB36: CUMPLE | AC36: CUMPLE | AD36: CUMPLE | AE36: CUMPLE | AF36: CUMPLE | AG36: CUMPLE | AH36: CUMPLE | AI36: CUMPLE | AJ36: CUMPLE | AK36: CUMPLE | AL36: CUMPLE | AM36: CUMPLE | AN36: CUMPLE | AO36: CUMPLE | AP36: CUMPLE | AQ36: CUMPLE | AR36: CUMPLE | AS36: CUMPLE | AT36: CUMPLE | AU36: CUMPLE | AV36: CUMPLE | AW36: CUMPLE | AY36: Cumple | AZ36: Cumple | BA36: Cumple | BB36: No
A37: 45856.258 | B37: Betuel olarte dussan | C37: OPERACIÓN | D37: SAN FRANCISCO | E37: WPT277 | F37: 71167 | G37: DIURNA | H37: CUMPLE | I37: CUMPLE | J37: CUMPLE | K37: CUMPLE | L37: CUMPLE | M37: CUMPLE | N37: CUMPLE | O37: CUMPLE | P37: CUMPLE | Q37: CUMPLE | R37: CUMPLE | S37: CUMPLE | T37: CUMPLE | U37: CUMPLE | V37: CUMPLE | W37: CUMPLE | X37: CUMPLE | Y37: CUMPLE | Z37: CUMPLE | AA37: CUMPLE | AB37: CUMPLE | AC37: NO APLICA | AD37: NO APLICA | AE37: NO APLICA | AF37: NO APLICA | AG37: CUMPLE | AH37: CUMPLE | AI37: CUMPLE | AJ37: CUMPLE | AK37: CUMPLE | AL37: CUMPLE | AM37: CUMPLE | AN37: CUMPLE | AO37: CUMPLE | AP37: CUMPLE | AQ37: CUMPLE | AR37: CUMPLE | AS37: CUMPLE | AT37: CUMPLE | AU37: CUMPLE | AV37: CUMPLE | AW37: CUMPLE | AY37: Cumple | AZ37: Cumple | BA37: Cumple | BB37: No
A38: 45856.268 | B38: Jhoan Tamayo Perdomo | C38: OPERACIÓN | D38: YAGUARA | E38: THS412 | F38: 37949 | G38: NO APLICA | H38: CUMPLE | I38: CUMPLE | J38: CUMPLE | K38: CUMPLE | L38: CUMPLE | M38: CUMPLE | N38: CUMPLE | O38: CUMPLE | P38: CUMPLE | Q38: NO CUMPLE | R38: CUMPLE | S38: CUMPLE | T38: CUMPLE | U38: CUMPLE | V38: CUMPLE | W38: CUMPLE | X38: CUMPLE | Y38: CUMPLE | Z38: CUMPLE | AA38: CUMPLE | AB38: CUMPLE | AC38: NO APLICA | AD38: NO APLICA | AE38: NO APLICA | AF38: NO APLICA | AG38: CUMPLE | AH38: CUMPLE | AI38: CUMPLE | AJ38: CUMPLE | AK38: CUMPLE | AL38: CUMPLE | AM38: CUMPLE | AN38: CUMPLE | AO38: CUMPLE | AP38: CUMPLE | AQ38: CUMPLE | AR38: CUMPLE | AS38: CUMPLE | AT38: CUMPLE | AU38: CUMPLE | AV38: CUMPLE | AW38: CUMPLE | AY38: Cumple | AZ38: Cumple | BA38: Cumple | BB38: No
A39: 45856.269 | B39: DEYMER BORRERO MOSQUERA | C39: OPERACIÓN | D39: TELLO | E39: WPT241 | F39: 60646 | G39: DIURNA | H39: CUMPLE | I39: CUMPLE | J39: CUMPLE | K39: CUMPLE | L39: CUMPLE | M39: CUMPLE | N39: CUMPLE | O39: CUMPLE | P39: CUMPLE | Q39: CUMPLE | R39: CUMPLE | S39: CUMPLE | T39: CUMPLE | U39: CUMPLE | V39: CUMPLE | W39: CUMPLE | X39: CUMPLE | Y39: CUMPLE | Z39: CUMPLE | AA39: CUMPLE | AB39: CUMPLE | AC39: NO APLICA | AD39: NO APLICA | AE39: NO APLICA | AF39: NO APLICA | AG39: CUMPLE | AH39: CUMPLE | AI39: CUMPLE | AJ39: CUMPLE | AK39: CUMPLE | AL39: CUMPLE | AM39: CUMPLE | AN39: CUMPLE | AO39: CUMPLE | AP39: CUMPLE | AQ39: CUMPLE | AR39: CUMPLE | AS39: CUMPLE | AT39: CUMPLE | AU39: CUMPLE | AV39: CUMPLE | AW39: CUMPLE | AY39: Cumple | AZ39: Cumple | BA39: Cumple | BB39: No
A40: 45856.275 | B40: Arbey Trujillo Castro | C40: OPERACIÓN | D40: YAGUARA | E40: Lpz1041 | F40: 317216 | G40: DIURNA | H40: CUMPLE | I40: CUMPLE | J40: CUMPLE | K40: CUMPLE | L40: CUMPLE | M40: CUMPLE | N40: CUMPLE | O40: CUMPLE | P40: CUMPLE | Q40: NO CUMPLE | R40: CUMPLE | S40: CUMPLE | T40: CUMPLE | U40: CUMPLE | V40: CUMPLE | W40: CUMPLE | X40: CUMPLE | Y40: CUMPLE | Z40: CUMPLE | AA40: CUMPLE | AB40: CUMPLE | AC40: CUMPLE | AD40: CUMPLE | AE40: CUMPLE | AF40: CUMPLE | AG40: CUMPLE | AH40: CUMPLE | AI40: CUMPLE | AJ40: CUMPLE | AK40: CUMPLE | AL40: CUMPLE | AM40: CUMPLE | AN40: CUMPLE | AO40: CUMPLE | AP40: CUMPLE | AQ40: CUMPLE | AR40: CUMPLE | AS40: CUMPLE | AT40: CUMPLE | AU40: CUMPLE | AV40: CUMPLE | AW40: CUMPLE | AY40: Cumple | AZ40: Cumple | BA40: Cumple | BB40: No
A41: 45856.293 | B41: YILBER LOSADA | C41: OPERACIÓN | D41: DINA | E41: WPT278 | F41: 137419 | G41: DIURNA | H41: CUMPLE | I41: CUMPLE | J41: CUMPLE | K41: CUMPLE | L41: CUMPLE | M41: CUMPLE | N41: CUMPLE | O41: CUMPLE | P41: CUMPLE | Q41: CUMPLE | R41: CUMPLE | S41: CUMPLE | T41: CUMPLE | U41: CUMPLE | V41: CUMPLE | W41: CUMPLE | X41: CUMPLE | Y41: CUMPLE | Z41: CUMPLE | AA41: CUMPLE | AB41: CUMPLE | AC41: NO APLICA | AD41: NO APLICA | AE41: NO APLICA | AF41: NO APLICA | AG41: CUMPLE | AH41: CUMPLE | AI41: CUMPLE | AJ41: CUMPLE | AK41: CUMPLE | AL41: CUMPLE | AM41: CUMPLE | AN41: CUMPLE | AO41: CUMPLE | AP41: CUMPLE | AQ41: CUMPLE | AR41: CUMPLE | AS41: CUMPLE | AT41: CUMPLE | AU41: CUMPLE | AV41: CUMPLE | AW41: CUMPLE | AX41: Cambio de aceite Actual 137419 Prox 136913 | AY41: Cumple | AZ41: Cumple | BA41: Cumple | BB41: No
A42: 45856.301 | B42: Carlos Andrés cabrera | C42: OPERACIÓN | D42: SAN FRANCISCO | E42: THQ021 | F42: 91680 | G42: DIURNA | H42: CUMPLE | I42: CUMPLE | J42: CUMPLE | K42: CUMPLE | L42: CUMPLE | M42: CUMPLE | N42: CUMPLE | O42: CUMPLE | P42: CUMPLE | Q42: CUMPLE | R42: CUMPLE | S42: CUMPLE | T42: CUMPLE | U42: CUMPLE | V42: CUMPLE | W42: CUMPLE | X42: CUMPLE | Y42: CUMPLE | Z42: CUMPLE | AA42: CUMPLE | AB42: CUMPLE | AC42: NO APLICA | AD42: NO APLICA | AE42: NO APLICA | AF42: NO APLICA | AG42: CUMPLE | AH42: CUMPLE | AI42: CUMPLE | AJ42: CUMPLE | AK42: CUMPLE | AL42: CUMPLE | AM42: CUMPLE | AN42: CUMPLE | AO42: CUMPLE | AP42: CUMPLE | AQ42: CUMPLE | AR42: CUMPLE | AS42: CUMPLE | AT42: CUMPLE | AU42: CUMPLE | AV42: CUMPLE | AW42: CUMPLE | AX42: Aire acondicionado dañado y radio FM | AY42: Cumple | AZ42: Cumple | BA42: Cumple | BB42: Si
A43: 45856.304 | B43: Jorge Lasso diaz | C43: OPERACIÓN | D43: DINA | E43: THQ136 | F43: 71409 | G43: DIURNA | H43: CUMPLE | I43: CUMPLE | J43: CUMPLE | K43: CUMPLE | L43: CUMPLE | M43: CUMPLE | N43: CUMPLE | O43: CUMPLE | P43: CUMPLE | Q43: CUMPLE | R43: CUMPLE | S43: CUMPLE | T43: CUMPLE | U43: CUMPLE | V43: CUMPLE | W43: CUMPLE | X43: CUMPLE | Y43: CUMPLE | Z43: CUMPLE | AA43: CUMPLE | AB43: CUMPLE | AC43: NO APLICA | AD43: NO APLICA | AE43: NO APLICA | AF43: NO APLICA | AG43: CUMPLE | AH43: CUMPLE | AI43: CUMPLE | AJ43: CUMPLE | AK43: CUMPLE | AL43: CUMPLE | AM43: CUMPLE | AN43: CUMPLE | AO43: CUMPLE | AP43: CUMPLE | AQ43: CUMPLE | AR43: CUMPLE | AS43: CUMPLE | AT43: CUMPLE | AU43: CUMPLE | AV43: CUMPLE | AW43: CUMPLE | AY43: Cumple | AZ43: Cumple | BA43: No cumple | BB43: No
A44: 45856.308 | B44: Aldemar González Lasso | C44: MANTENIMIENTO (CONSORCIO SAS-CFP) | D44: SAN FRANCISCO | E44: THS530 | F44: 55476 | G44: DIURNA | H44: CUMPLE | I44: CUMPLE | J44: CUMPLE | K44: CUMPLE | L44: CUMPLE | M44: CUMPLE | N44: CUMPLE | O44: CUMPLE | P44: CUMPLE | Q44: CUMPLE | R44: CUMPLE | S44: CUMPLE | T44: CUMPLE | U44: CUMPLE | V44: CUMPLE | W44: CUMPLE | X44: CUMPLE | Y44: CUMPLE | Z44: CUMPLE | AA44: CUMPLE | AB44: CUMPLE | AC44: NO APLICA | AD44: NO APLICA | AE44: NO APLICA | AF44: NO APLICA | AG44: CUMPLE | AH44: CUMPLE | AI44: CUMPLE | AJ44: CUMPLE | AK44: CUMPLE | AL44: CUMPLE | AM44: CUMPLE | AN44: CUMPLE | AO44: CUMPLE | AP44: CUMPLE | AQ44: CUMPLE | AR44: CUMPLE | AS44: CUMPLE | AT44: CUMPLE | AU44: CUMPLE | AV44: CUMPLE | AW44: CUMPLE | AX44: Sin novedad | AY44: Cumple | AZ44: Cumple | BA44: Cumple | BB44: No
A45: 45856.312 | B45: Sergio Barreto | C45: OPERACIÓN | D45: TELLO | E45: THS658 | F45: 940 | G45: DIURNA | H45: CUMPLE | I45: CUMPLE | J45: CUMPLE | K45: CUMPLE | L45: CUMPLE | M45: CUMPLE | N45: CUMPLE | O45: CUMPLE | P45: CUMPLE | Q45: CUMPLE | R45: CUMPLE | S45: CUMPLE | T45: CUMPLE | U45: CUMPLE | V45: CUMPLE | W45: CUMPLE | X45: CUMPLE | Y45: CUMPLE | Z45: CUMPLE | AA45: CUMPLE | AB45: CUMPLE | AC45: NO APLICA | AD45: NO APLICA | AE45: NO APLICA | AF45: NO APLICA | AG45: CUMPLE | AH45: CUMPLE | AI45: CUMPLE | AJ45: CUMPLE | AK45: CUMPLE | AL45: CUMPLE | AM45: CUMPLE | AN45: CUMPLE | AO45: CUMPLE | AP45: CUMPLE | AQ45: CUMPLE | AR45: CUMPLE | AS45: CUMPLE | AT45: CUMPLE | AU45: CUMPLE | AV45: CUMPLE | AW45: CUMPLE | AY45: Cumple | AZ45: Cumple | BA45: Cumple | BB45: No
A46: 45856.317 | B46: Jorge Mosquera | C46: OPERACIÓN | D46: TELLO | E46: NTQ 466 | F46: 5338 | G46: DIURNA | H46: CUMPLE | I46: CUMPLE | J46: CUMPLE | K46: CUMPLE | L46: CUMPLE | M46: CUMPLE | N46: CUMPLE | O46: CUMPLE | P46: CUMPLE | Q46: CUMPLE | R46: CUMPLE | S46: CUMPLE | T46: CUMPLE | U46: CUMPLE | V46: CUMPLE | W46: CUMPLE | X46: CUMPLE | Y46: CUMPLE | Z46: CUMPLE | AA46: CUMPLE | AB46: CUMPLE | AC46: CUMPLE | AD46: CUMPLE | AE46: CUMPLE | AF46: CUMPLE | AG46: CUMPLE | AH46: CUMPLE | AI46: CUMPLE | AJ46: CUMPLE | AK46: CUMPLE | AL46: CUMPLE | AM46: CUMPLE | AN46: CUMPLE | AO46: CUMPLE | AP46: CUMPLE | AQ46: CUMPLE | AR46: CUMPLE | AS46: CUMPLE | AT46: CUMPLE | AU46: CUMPLE | AV46: CUMPLE | AW46: CUMPLE | AY46: Cumple | AZ46: Cumple | BA46: Cumple | BB46: No
A47: 45856.342 | B47: Eladio Perdomo Pérez | C47: MANTENIMIENTO (CONSORCIO SAS-CFP) | D47: DINA | E47: THP849 | F47: 130347 | G47: DIURNA | H47: CUMPLE | I47: CUMPLE | J47: CUMPLE | K47: CUMPLE | L47: CUMPLE | M47: CUMPLE | N47: CUMPLE | O47: CUMPLE | P47: CUMPLE | Q47: CUMPLE | R47: CUMPLE | S47: CUMPLE | T47: CUMPLE | U47: CUMPLE | V47: CUMPLE | W47: CUMPLE | X47: CUMPLE | Y47: CUMPLE | Z47: CUMPLE | AA47: CUMPLE | AB47: CUMPLE | AC47: NO APLICA | AD47: NO APLICA | AE47: NO APLICA | AF47: NO APLICA | AG47: CUMPLE | AH47: CUMPLE | AI47: CUMPLE | AJ47: CUMPLE | AK47: CUMPLE | AL47: CUMPLE | AM47: CUMPLE | AN47: CUMPLE | AO47: CUMPLE | AP47: CUMPLE | AQ47: CUMPLE | AR47: CUMPLE | AS47: CUMPLE | AT47: CUMPLE | AU47: CUMPLE | AV47: CUMPLE | AW47: CUMPLE | AY47: Cumple | AZ47: Cumple | BA47: Cumple | BB47: No
A48: 45857.219 | B48: Jose Miller Escobar Tello | C48: OPERACIÓN | D48: TELLO | E48: Lhw. 521 | F48: 86424 | G48: DIURNA | H48: CUMPLE | I48: CUMPLE | J48: CUMPLE | K48: CUMPLE | L48: CUMPLE | M48: CUMPLE | N48: CUMPLE | O48: CUMPLE | P48: CUMPLE | Q48: CUMPLE | R48: CUMPLE | S48: CUMPLE | T48: CUMPLE | U48: CUMPLE | V48: CUMPLE | W48: CUMPLE | X48: CUMPLE | Y48: CUMPLE | Z48: CUMPLE | AA48: CUMPLE | AB48: CUMPLE | AC48: CUMPLE | AD48: CUMPLE | AE48: CUMPLE | AF48: CUMPLE | AG48: CUMPLE | AH48: NO CUMPLE | AI48: CUMPLE | AJ48: CUMPLE | AK48: CUMPLE | AL48: CUMPLE | AM48: CUMPLE | AN48: CUMPLE | AO48: CUMPLE | AP48: CUMPLE | AQ48: CUMPLE | AR48: CUMPLE | AS48: CUMPLE | AT48: CUMPLE | AU48: CUMPLE | AV48: CUMPLE | AW48: CUMPLE | AY48: Cumple | AZ48: Cumple | BA48: Cumple | BB48: No
A49: 45857.287 | B49: Wilson Variaza | C49: OPERACIÓN | D49: DINA | E49: Wpt278 | F49: 137474 | G49: DIURNA | H49: CUMPLE | I49: CUMPLE | J49: CUMPLE | K49: CUMPLE | L49: CUMPLE | M49: CUMPLE | N49: CUMPLE | O49: CUMPLE | P49: CUMPLE | Q49: CUMPLE | R49: CUMPLE | S49: CUMPLE | T49: CUMPLE | U49: CUMPLE | V49: CUMPLE | W49: CUMPLE | X49: CUMPLE | Y49: CUMPLE | Z49: CUMPLE | AA49: CUMPLE | AB49: CUMPLE | AC49: CUMPLE | AD49: CUMPLE | AE49: CUMPLE | AF49: NO APLICA | AG49: CUMPLE | AH49: CUMPLE | AI49: CUMPLE | AJ49: CUMPLE | AK49: CUMPLE | AL49: CUMPLE | AM49: CUMPLE | AN49: CUMPLE | AO49: CUMPLE | AP49: CUMPLE | AQ49: CUMPLE | AR49: CUMPLE | AS49: CUMPLE | AT49: CUMPLE | AU49: CUMPLE | AV49: CUMPLE | AW49: CUMPLE | AX49: Tiene ralones leves en partes de la cabina | AY49: Cumple | AZ49: Cumple | BA49: Cumple | BB49: No
A50: 45858.212 | B50: Jose Miller Escobar Tello | C50: OPERACIÓN | D50: TELLO | E50: Lhw. 521 | F50: 86567 | G50: DIURNA | H50: CUMPLE | I50: CUMPLE | J50: CUMPLE | K50: CUMPLE | L50: CUMPLE | M50: CUMPLE | N50: CUMPLE | O50: CUMPLE | P50: CUMPLE | Q50: CUMPLE | R50: CUMPLE | S50: CUMPLE | T50: CUMPLE | U50: CUMPLE | V50: CUMPLE | W50: CUMPLE | X50: CUMPLE | Y50: CUMPLE | Z50: CUMPLE | AA50: CUMPLE | AB50: CUMPLE | AC50: CUMPLE | AD50: CUMPLE | AE50: CUMPLE | AF50: CUMPLE | AG50: CUMPLE | AH50: CUMPLE | AI50: CUMPLE | AJ50: CUMPLE | AK50: CUMPLE | AL50: CUMPLE | AM50: CUMPLE | AN50: CUMPLE | AO50: CUMPLE | AP50: CUMPLE | AQ50: CUMPLE | AR50: CUMPLE | AS50: CUMPLE | AT50: CUMPLE | AU50: CUMPLE | AV50: CUMPLE | AW50: CUMPLE | AY50: Cumple | AZ50: Cumple | BA50: Cumple | BB50: No
A51: 45858.278 | B51: Javier Alfonso Amaya Suárez | C51: MANTENIMIENTO (CONSORCIO SAS-CFP) | D51: DINA | E51: WPT354 | F51: 123249 | G51: DIURNA | H51: CUMPLE | I51: CUMPLE | J51: CUMPLE | K51: CUMPLE | L51: CUMPLE | M51: CUMPLE | N51: CUMPLE | O51: CUMPLE | P51: CUMPLE | Q51: CUMPLE | R51: CUMPLE | S51: CUMPLE | T51: CUMPLE | U51: CUMPLE | V51: CUMPLE | W51: CUMPLE | X51: CUMPLE | Y51: CUMPLE | Z51: CUMPLE | AA51: CUMPLE | AB51: CUMPLE | AC51: NO APLICA | AD51: CUMPLE | AE51: CUMPLE | AF51: CUMPLE | AG51: CUMPLE | AH51: CUMPLE | AI51: CUMPLE | AJ51: CUMPLE | AK51: CUMPLE | AL51: CUMPLE | AM51: CUMPLE | AN51: NO CUMPLE | AO51: CUMPLE | AP51: CUMPLE | AQ51: CUMPLE | AR51: CUMPLE | AS51: CUMPLE | AT51: CUMPLE | AU51: CUMPLE | AV51: CUMPLE | AW51: CUMPLE | AX51: Presenta ruido en la correa de accesorios, la silla del copiloto se unde, las llantas traceras están desgastadas, la manija del lado derecho puerta tracera dañada por cristalización de material, perno de la llantera tracera dañado. | AY51: Cumple | AZ51: Cumple | BA51: Cumple | BB51: Si
A52: 45859.262 | B52: Eladio Perdomo Pérez | C52: MANTENIMIENTO (CONSORCIO SAS-CFP) | D52: DINA | E52: THP849 | F52: 130359 | G52: DIURNA | H52: CUMPLE | I52: CUMPLE | J52: CUMPLE | K52: CUMPLE | L52: CUMPLE | M52: CUMPLE | N52: CUMPLE | O52: CUMPLE | P52: CUMPLE | Q52: CUMPLE | R52: CUMPLE | S52: CUMPLE | T52: CUMPLE | U52: CUMPLE | V52: CUMPLE | W52: CUMPLE | X52: CUMPLE | Y52: CUMPLE | Z52: CUMPLE | AA52: CUMPLE | AB52: CUMPLE | AC52: NO APLICA | AD52: NO APLICA | AE52: NO APLICA | AF52: NO APLICA | AG52: CUMPLE | AH52: CUMPLE | AI52: CUMPLE | AJ52: CUMPLE | AK52: CUMPLE | AL52: CUMPLE | AM52: CUMPLE | AN52: CUMPLE | AO52: CUMPLE | AP52: CUMPLE | AQ52: CUMPLE | AR52: CUMPLE | AS52: CUMPLE | AT52: CUMPLE | AU52: CUMPLE | AV52: CUMPLE | AW52: CUMPLE | AY52: Cumple | AZ52: Cumple | BA52: Cumple | BB52: No
A53: 45859.268 | B53: DEYMER BORRERO MOSQUERA | C53: OPERACIÓN | D53: TELLO | E53: WPT241 | F53: 60664 | G53: DIURNA | H53: CUMPLE | I53: CUMPLE | J53: CUMPLE | K53: CUMPLE | L53: CUMPLE | M53: CUMPLE | N53: CUMPLE | O53: CUMPLE | P53: CUMPLE | Q53: CUMPLE | R53: CUMPLE | S53: CUMPLE | T53: CUMPLE | U53: CUMPLE | V53: CUMPLE | W53: CUMPLE | X53: CUMPLE | Y53: CUMPLE | Z53: CUMPLE | AA53: CUMPLE | AB53: CUMPLE | AC53: NO APLICA | AD53: NO APLICA | AE53: NO APLICA | AF53: NO APLICA | AG53: CUMPLE | AH53: CUMPLE | AI53: CUMPLE | AJ53: CUMPLE | AK53: CUMPLE | AL53: CUMPLE | AM53: CUMPLE | AN53: CUMPLE | AO53: CUMPLE | AP53: CUMPLE | AQ53: CUMPLE | AR53: CUMPLE | AS53: CUMPLE | AT53: CUMPLE | AU53: CUMPLE | AV53: CUMPLE | AW53: CUMPLE | AY53: Cumple | AZ53: Cumple | BA53: Cumple | BB53: No
A54: 45859.272 | B54: Hernan David Menza | C54: OPERACIÓN | D54: YAGUARA | E54: LPZ104 | F54: 37254 | G54: DIURNA | H54: CUMPLE | I54: CUMPLE | J54: CUMPLE | K54: CUMPLE | L54: CUMPLE | M54: CUMPLE | N54: CUMPLE | O54: CUMPLE | P54: CUMPLE | Q54: NO CUMPLE | R54: CUMPLE | S54: CUMPLE | T54: CUMPLE | U54: CUMPLE | V54: CUMPLE | W54: CUMPLE | X54: CUMPLE | Y54: CUMPLE | Z54: CUMPLE | AA54: CUMPLE | AB54: CUMPLE | AC54: CUMPLE | AD54: CUMPLE | AE54: CUMPLE | AF54: CUMPLE | AG54: CUMPLE | AH54: CUMPLE | AI54: CUMPLE | AJ54: CUMPLE | AK54: CUMPLE | AL54: CUMPLE | AM54: CUMPLE | AN54: CUMPLE | AO54: CUMPLE | AP54: CUMPLE | AQ54: CUMPLE | AR54: CUMPLE | AS54: CUMPLE | AT54: CUMPLE | AU54: CUMPLE | AV54: CUMPLE | AW54: CUMPLE | AY54: Cumple | AZ54: Cumple | BA54: Cumple | BB54: No
A55: 45859.292 | B55: YILBER LOSADA | C55: OPERACIÓN | D55: DINA | E55: WPT278 | F55: 137540 | G55: DIURNA | H55: CUMPLE | I55: CUMPLE | J55: CUMPLE | K55: CUMPLE | L55: CUMPLE | M55: CUMPLE | N55: CUMPLE | O55: CUMPLE | P55: CUMPLE | Q55: CUMPLE | R55: CUMPLE | S55: CUMPLE | T55: CUMPLE | U55: CUMPLE | V55: CUMPLE | W55: CUMPLE | X55: CUMPLE | Y55: CUMPLE | Z55: CUMPLE | AA55: CUMPLE | AB55: CUMPLE | AC55: NO APLICA | AD55: NO APLICA | AE55: NO APLICA | AF55: NO APLICA | AG55: CUMPLE | AH55: CUMPLE | AI55: CUMPLE | AJ55: CUMPLE | AK55: CUMPLE | AL55: CUMPLE | AM55: CUMPLE | AN55: CUMPLE | AO55: CUMPLE | AP55: CUMPLE | AQ55: CUMPLE | AR55: CUMPLE | AS55: CUMPLE | AT55: CUMPLE | AU55: CUMPLE | AV55: CUMPLE | AW55: CUMPLE | AX55: Hacer cambio de aceite | AY55: Cumple | AZ55: Cumple | BA55: Cumple | BB55: No
A56: 45859.293 | B56: Carlos Andrés Cabrera | C56: OPERACIÓN | D56: SAN FRANCISCO | E56: THQ021 | F56: 91714 | G56: DIURNA | H56: CUMPLE | I56: CUMPLE | J56: CUMPLE | K56: CUMPLE | L56: CUMPLE | M56: CUMPLE | N56: CUMPLE | O56: CUMPLE | P56: CUMPLE | Q56: CUMPLE | R56: CUMPLE | S56: CUMPLE | T56: CUMPLE | U56: CUMPLE | V56: CUMPLE | W56: CUMPLE | X56: CUMPLE | Y56: CUMPLE | Z56: CUMPLE | AA56: CUMPLE | AB56: CUMPLE | AC56: NO APLICA | AD56: NO APLICA | AE56: NO APLICA | AF56: NO APLICA | AG56: CUMPLE | AH56: CUMPLE | AI56: CUMPLE | AJ56: CUMPLE | AK56: CUMPLE | AL56: CUMPLE | AM56: CUMPLE | AN56: CUMPLE | AO56: CUMPLE | AP56: CUMPLE | AQ56: CUMPLE | AR56: CUMPLE | AS56: CUMPLE | AT56: CUMPLE | AU56: CUMPLE | AV56: CUMPLE | AW56: CUMPLE | AX56: Aire acondicionado dañado y radio FM | AY56: Cumple | AZ56: Cumple | BA56: Cumple | BB56: No
A57: 45859.297 | B57: Betuel olarte dussan | C57: OPERACIÓN | D57: SAN FRANCISCO | E57: WPT277 | F57: 71197 | G57: DIURNA | H57: CUMPLE | I57: CUMPLE | J57: CUMPLE | K57: CUMPLE | L57: CUMPLE | M57: CUMPLE | N57: CUMPLE | O57: CUMPLE | P57: CUMPLE | Q57: CUMPLE | R57: CUMPLE | S57: CUMPLE | T57: CUMPLE | U57: CUMPLE | V57: CUMPLE | W57: CUMPLE | X57: CUMPLE | Y57: CUMPLE | Z57: CUMPLE | AA57: CUMPLE | AB57: CUMPLE | AC57: NO APLICA | AD57: NO APLICA | AE57: NO APLICA | AF57: NO APLICA | AG57: CUMPLE | AH57: CUMPLE | AI57: CUMPLE | AJ57: CUMPLE | AK57: CUMPLE | AL57: CUMPLE | AM57: CUMPLE | AN57: CUMPLE | AO57: CUMPLE | AP57: CUMPLE | AQ57: CUMPLE | AR57: CUMPLE | AS57: CUMPLE | AT57: CUMPLE | AU57: CUMPLE | AV57: CUMPLE | AW57: CUMPLE | AY57: Cumple | AZ57: Cumple | BA57: Cumple | BB57: No
A58: 45859.299 | B58: Sergio Barreto | C58: OPERACIÓN | D58: TELLO | E58: THS658 | F58: 1023 | G58: DIURNA | H58: CUMPLE | I58: CUMPLE | J58: CUMPLE | K58: CUMPLE | L58: CUMPLE | M58: CUMPLE | N58: CUMPLE | O58: CUMPLE | P58: CUMPLE | Q58: CUMPLE | R58: CUMPLE | S58: CUMPLE | T58: CUMPLE | U58: CUMPLE | V58: CUMPLE | W58: CUMPLE | X58: CUMPLE | Y58: CUMPLE | Z58: CUMPLE | AA58: CUMPLE | AB58: CUMPLE | AC58: NO APLICA | AD58: NO APLICA | AE58: NO APLICA | AF58: NO APLICA | AG58: CUMPLE | AH58: CUMPLE | AI58: CUMPLE | AJ58: CUMPLE | AK58: CUMPLE | AL58: CUMPLE | AM58: CUMPLE | AN58: CUMPLE | AO58: CUMPLE | AP58: CUMPLE | AQ58: CUMPLE | AR58: CUMPLE | AS58: CUMPLE | AT58: CUMPLE | AU58: CUMPLE | AV58: CUMPLE | AW58: CUMPLE | AY58: Cumple | AZ58: Cumple | BA58: Cumple | BB58: No
A59: 45859.301 | B59: Aldemar González Lasso | C59: MANTENIMIENTO (CONSORCIO SAS-CFP) | D59: SAN FRANCISCO | E59: THS530 | F59: 55501 | G59: DIURNA | H59: CUMPLE | I59: CUMPLE | J59: CUMPLE | K59: CUMPLE | L59: CUMPLE | M59: CUMPLE | N59: CUMPLE | O59: CUMPLE | P59: CUMPLE | Q59: CUMPLE | R59: CUMPLE | S59: CUMPLE | T59: CUMPLE | U59: CUMPLE | V59: CUMPLE | W59: CUMPLE | X59: CUMPLE | Y59: CUMPLE | Z59: CUMPLE | AA59: CUMPLE | AB59: CUMPLE | AC59: NO APLICA | AD59: NO APLICA | AE59: NO APLICA | AF59: NO APLICA | AG59: CUMPLE | AH59: CUMPLE | AI59: CUMPLE | AJ59: CUMPLE | AK59: CUMPLE | AL59: CUMPLE | AM59: CUMPLE | AN59: CUMPLE | AO59: CUMPLE | AP59: CUMPLE | AQ59: CUMPLE | AR59: CUMPLE | AS59: CUMPLE | AT59: CUMPLE | AU59: CUMPLE | AV59: CUMPLE | AW59: CUMPLE | AX59: Sin novedad | AY59: Cumple | AZ59: Cumple | BA59: Cumple | BB59: No
A60: 45859.315 | B60: Jhoan Tamayo Perdomo | C60: OPERACIÓN | D60: YAGUARA | E60: THS412 | F60: 37965 | G60: NO APLICA | H60: CUMPLE | I60: CUMPLE | J60: CUMPLE | K60: CUMPLE | L60: CUMPLE | M60: CUMPLE | N60: CUMPLE | O60: CUMPLE | P60: CUMPLE | Q60: NO CUMPLE | R60: CUMPLE | S60: CUMPLE | T60: CUMPLE | U60: CUMPLE | V60: CUMPLE | W60: CUMPLE | X60: CUMPLE | Y60: CUMPLE | Z60: CUMPLE | AA60: CUMPLE | AB60: CUMPLE | AC60: NO APLICA | AD60: NO APLICA | AE60: NO APLICA | AF60: NO APLICA | AG60: CUMPLE | AH60: CUMPLE | AI60: CUMPLE | AJ60: CUMPLE | AK60: CUMPLE | AL60: CUMPLE | AM60: CUMPLE | AN60: CUMPLE | AO60: CUMPLE | AP60: CUMPLE | AQ60: CUMPLE | AR60: CUMPLE | AS60: CUMPLE | AT60: CUMPLE | AU60: CUMPLE | AV60: CUMPLE | AW60: CUMPLE | AY60: Cumple | AZ60: Cumple | BA60: Cumple | BB60: No
A61: 45859.321 | B61: Jorge Lasso diaz | C61: OPERACIÓN | D61: DINA | E61: THQ 136 | F61: 71409 | G61: DIURNA | H61: CUMPLE | I61: CUMPLE | J61: CUMPLE | K61: CUMPLE | L61: CUMPLE | M61: CUMPLE | N61: CUMPLE | O61: CUMPLE | P61: CUMPLE | Q61: CUMPLE | R61: CUMPLE | S61: CUMPLE | T61: CUMPLE | U61: CUMPLE | V61: CUMPLE | W61: CUMPLE | X61: CUMPLE | Y61: CUMPLE | Z61: CUMPLE | AA61: CUMPLE | AB61: CUMPLE | AC61: NO APLICA | AD61: NO APLICA | AE61: NO APLICA | AF61: NO APLICA | AG61: CUMPLE | AH61: CUMPLE | AI61: CUMPLE | AJ61: CUMPLE | AK61: CUMPLE | AL61: CUMPLE | AM61: CUMPLE | AN61: CUMPLE | AO61: CUMPLE | AP61: CUMPLE | AQ61: CUMPLE | AR61: CUMPLE | AS61: CUMPLE | AT61: CUMPLE | AU61: CUMPLE | AV61: CUMPLE | AW61: CUMPLE | AY61: Cumple | AZ61: Cumple | BA61: Cumple | BB61: No
A62: 45859.344 | B62: Miller Jesús charry | C62: OPERACIÓN | D62: SAN FRANCISCO | E62: Wpt -245 | F62: 110446 | G62: DIURNA | H62: CUMPLE | I62: CUMPLE | J62: CUMPLE | K62: CUMPLE | L62: CUMPLE | M62: NO CUMPLE | N62: CUMPLE | O62: CUMPLE | P62: CUMPLE | Q62: CUMPLE | R62: CUMPLE | S62: CUMPLE | T62: CUMPLE | U62: CUMPLE | V62: CUMPLE | W62: CUMPLE | X62: CUMPLE | Y62: CUMPLE | Z62: CUMPLE | AA62: CUMPLE | AB62: CUMPLE | AC62: NO APLICA | AD62: NO APLICA | AE62: NO APLICA | AF62: NO APLICA | AG62: CUMPLE | AH62: CUMPLE | AI62: CUMPLE | AJ62: CUMPLE | AK62: CUMPLE | AL62: CUMPLE | AM62: CUMPLE | AN62: CUMPLE | AO62: CUMPLE | AP62: CUMPLE | AQ62: CUMPLE | AR62: CUMPLE | AS62: CUMPLE | AT62: CUMPLE | AU62: CUMPLE | AV62: CUMPLE | AW62: CUMPLE | AY62: Cumple | AZ62: Cumple | BA62: Cumple | BB62: No
A63: 45859.353 | B63: José Vicente Álvarez Arias | C63: OPERACIÓN | D63: DINA | E63: WPT246 | F63: 90311 | G63: DIURNA | H63: CUMPLE | I63: CUMPLE | J63: CUMPLE | K63: CUMPLE | L63: CUMPLE | M63: CUMPLE | N63: CUMPLE | O63: CUMPLE | P63: CUMPLE | Q63: CUMPLE | R63: CUMPLE | S63: CUMPLE | T63: NO CUMPLE | U63: CUMPLE | V63: CUMPLE | W63: CUMPLE | X63: CUMPLE | Y63: CUMPLE | Z63: CUMPLE | AA63: CUMPLE | AB63: CUMPLE | AC63: NO APLICA | AD63: NO APLICA | AE63: NO APLICA | AF63: NO APLICA | AG63: CUMPLE | AH63: CUMPLE | AI63: CUMPLE | AJ63: CUMPLE | AK63: CUMPLE | AL63: CUMPLE | AM63: CUMPLE | AN63: CUMPLE | AO63: CUMPLE | AP63: CUMPLE | AQ63: CUMPLE | AR63: CUMPLE | AS63: CUMPLE | AT63: CUMPLE | AU63: CUMPLE | AV63: CUMPLE | AW63: CUMPLE | AX63: Sin vidrio en lateral izquierdo ,falta de ajustes en puertas , carroceria en malas condiciones, no tiene pitó de reversa , antivolco doblado | AY63: Cumple | AZ63: Cumple | BA63: Cumple | BB63: No
A64: 45859.355 | B64: Michel aroca Medina | C64: OPERACIÓN | D64: SAN FRANCISCO | E64: WPT 243 | F64: 96078 | G64: DIURNA | H64: CUMPLE | I64: CUMPLE | J64: CUMPLE | K64: CUMPLE | L64: CUMPLE | M64: CUMPLE | N64: CUMPLE | O64: CUMPLE | P64: CUMPLE | Q64: CUMPLE | R64: CUMPLE | S64: CUMPLE | T64: CUMPLE | U64: CUMPLE | V64: CUMPLE | W64: CUMPLE | X64: CUMPLE | Y64: CUMPLE | Z64: CUMPLE | AA64: CUMPLE | AB64: CUMPLE | AC64: NO APLICA | AD64: NO APLICA | AE64: NO APLICA | AF64: NO APLICA | AG64: CUMPLE | AH64: CUMPLE | AI64: CUMPLE | AJ64: CUMPLE | AK64: CUMPLE | AL64: CUMPLE | AM64: CUMPLE | AN64: CUMPLE | AO64: CUMPLE | AP64: CUMPLE | AQ64: CUMPLE | AR64: CUMPLE | AS64: CUMPLE | AT64: CUMPLE | AU64: CUMPLE | AV64: CUMPLE | AW64: CUMPLE | AX64: Hay que hacerle la alineación | AY64: Cumple | AZ64: Cumple | BA64: Cumple | BB64: No
A65: 45859.527 | B65: Alejandro aguja perez | C65: MANTENIMIENTO (CONSORCIO SAS-CFP) | D65: DINA | E65: Ths544 | F65: 42725 | G65: DIURNA | H65: CUMPLE | I65: CUMPLE | J65: CUMPLE | K65: CUMPLE | L65: CUMPLE | M65: CUMPLE | N65: CUMPLE | O65: CUMPLE | P65: CUMPLE | Q65: CUMPLE | R65: CUMPLE | S65: CUMPLE | T65: CUMPLE | U65: CUMPLE | V65: CUMPLE | W65: CUMPLE | X65: CUMPLE | Y65: CUMPLE | Z65: CUMPLE | AA65: CUMPLE | AB65: CUMPLE | AC65: NO APLICA | AD65: NO APLICA | AE65: NO APLICA | AF65: NO APLICA | AG65: CUMPLE | AH65: CUMPLE | AI65: CUMPLE | AJ65: CUMPLE | AK65: CUMPLE | AL65: CUMPLE | AM65: CUMPLE | AN65: CUMPLE | AO65: CUMPLE | AP65: CUMPLE | AQ65: CUMPLE | AR65: CUMPLE | AS65: CUMPLE | AT65: CUMPLE | AU65: CUMPLE | AV65: CUMPLE | AW65: CUMPLE | AY65: Cumple | AZ65: Cumple | BA65: Cumple | BB65: Si
A66: 45859.529 | B66: Alejandro aguja perez | C66: MANTENIMIENTO (CONSORCIO SAS-CFP) | D66: DINA | E66: Ths544 | F66: 42942 | G66: DIURNA | H66: CUMPLE | I66: CUMPLE | J66: CUMPLE | K66: CUMPLE | L66: CUMPLE | M66: CUMPLE | N66: CUMPLE | O66: CUMPLE | P66: CUMPLE | Q66: CUMPLE | R66: CUMPLE | S66: CUMPLE | T66: CUMPLE | U66: CUMPLE | V66: CUMPLE | W66: CUMPLE | X66: CUMPLE | Y66: CUMPLE | Z66: CUMPLE | AA66: CUMPLE | AB66: CUMPLE | AC66: NO APLICA | AD66: NO APLICA | AE66: NO APLICA | AF66: NO APLICA | AG66: CUMPLE | AH66: CUMPLE | AI66: CUMPLE | AJ66: CUMPLE | AK66: CUMPLE | AL66: CUMPLE | AM66: CUMPLE | AN66: CUMPLE | AO66: CUMPLE | AP66: CUMPLE | AQ66: CUMPLE | AR66: CUMPLE | AS66: CUMPLE | AT66: CUMPLE | AU66: CUMPLE | AV66: CUMPLE | AW66: CUMPLE | AY66: Cumple | AZ66: Cumple | BA66: Cumple | BB66: Si
A67: 45859.593 | B67: Gerardo ariza | C67: MANTENIMIENTO (CONSORCIO SAS-CFP) | D67: DINA | E67: EQZ742 | F67: 65800 | G67: DIURNA | H67: CUMPLE | I67: CUMPLE | J67: CUMPLE | K67: CUMPLE | L67: CUMPLE | M67: CUMPLE | N67: NO CUMPLE | O67: CUMPLE | P67: CUMPLE | Q67: CUMPLE | R67: CUMPLE | S67: CUMPLE | T67: CUMPLE | U67: CUMPLE | V67: CUMPLE | W67: CUMPLE | X67: CUMPLE | Y67: CUMPLE | Z67: CUMPLE | AA67: CUMPLE | AB67: CUMPLE | AC67: CUMPLE | AD67: CUMPLE | AE67: CUMPLE | AF67: NO APLICA | AG67: CUMPLE | AH67: CUMPLE | AI67: CUMPLE | AJ67: CUMPLE | AK67: CUMPLE | AL67: CUMPLE | AM67: CUMPLE | AN67: CUMPLE | AO67: CUMPLE | AP67: CUMPLE | AQ67: CUMPLE | AR67: CUMPLE | AS67: CUMPLE | AT67: CUMPLE | AU67: CUMPLE | AV67: CUMPLE | AW67: CUMPLE | AX67: Pendiente cambio panorámico, suministrar herramienta básicas, llantas traceras pequeñas, vías en mal estado, Pendiente cambio sensor de combustible, lavado general | AY67: Cumple | AZ67: Cumple | BA67: Cumple | BB67: No
A68: 45859.598 | B68: Juan Zabala | C68: OPERACIÓN | D68: TELLO | E68: NTQ466 | F68: 5400 | G68: DIURNA | H68: CUMPLE | I68: CUMPLE | J68: CUMPLE | K68: CUMPLE | L68: CUMPLE | M68: CUMPLE | N68: CUMPLE | O68: CUMPLE | P68: CUMPLE | Q68: CUMPLE | R68: CUMPLE | S68: CUMPLE | T68: CUMPLE | U68: CUMPLE | V68: CUMPLE | W68: CUMPLE | X68: CUMPLE | Y68: CUMPLE | Z68: CUMPLE | AA68: CUMPLE | AB68: CUMPLE | AC68: CUMPLE | AD68: CUMPLE | AE68: CUMPLE | AF68: CUMPLE | AG68: CUMPLE | AH68: CUMPLE | AI68: CUMPLE | AJ68: CUMPLE | AK68: CUMPLE | AL68: CUMPLE | AM68: CUMPLE | AN68: CUMPLE | AO68: CUMPLE | AP68: CUMPLE | AQ68: CUMPLE | AR68: CUMPLE | AS68: CUMPLE | AT68: CUMPLE | AU68: CUMPLE | AV68: CUMPLE | AW68: CUMPLE | AY68: Cumple | AZ68: Cumple | BA68: Cumple | BB68: No
A69: 45859.692 | B69: Capitolino mateus | C69: MANTENIMIENTO (CONSORCIO SAS-CFP) | D69: DINA | E69: Eqz286 | F69: 95130 | G69: DIURNA | H69: CUMPLE | I69: CUMPLE | J69: CUMPLE | K69: CUMPLE | L69: CUMPLE | M69: CUMPLE | N69: CUMPLE | O69: CUMPLE | P69: CUMPLE | Q69: CUMPLE | R69: CUMPLE | S69: CUMPLE | T69: CUMPLE | U69: CUMPLE | V69: CUMPLE | W69: CUMPLE | X69: CUMPLE | Y69: CUMPLE | Z69: CUMPLE | AA69: CUMPLE | AB69: CUMPLE | AC69: NO APLICA | AD69: NO APLICA | AE69: NO APLICA | AF69: NO APLICA | AG69: CUMPLE | AH69: CUMPLE | AI69: CUMPLE | AJ69: CUMPLE | AK69: CUMPLE | AL69: CUMPLE | AM69: CUMPLE | AN69: CUMPLE | AO69: CUMPLE | AP69: CUMPLE | AQ69: CUMPLE | AR69: CUMPLE | AS69: CUMPLE | AT69: CUMPLE | AU69: CUMPLE | AV69: CUMPLE | AW69: CUMPLE | AX69: Cambio de cinturón lado conductor por recomendación del cliente Arreglo de silla conductor y pasajero tapicería Cambio de cinta reflectiva del contorno del vehículo obligatorio por el organismo de transito | AY69: Cumple | AZ69: Cumple | BA69: Cumple | BB69: No
A70: 45859.702 | B70: Jose Miller Escobar Tello | C70: OPERACIÓN | D70: TELLO | E70: Lhw | F70: 86834 | G70: NOCTURNA | H70: CUMPLE | I70: CUMPLE | J70: CUMPLE | K70: CUMPLE | L70: CUMPLE | M70: CUMPLE | N70: CUMPLE | O70: CUMPLE | P70: CUMPLE | Q70: CUMPLE | R70: CUMPLE | S70: CUMPLE | T70: CUMPLE | U70: CUMPLE | V70: CUMPLE | W70: CUMPLE | X70: CUMPLE | Y70: CUMPLE | Z70: CUMPLE | AA70: CUMPLE | AB70: CUMPLE | AC70: CUMPLE | AD70: CUMPLE | AE70: CUMPLE | AF70: CUMPLE | AG70: CUMPLE | AH70: CUMPLE | AI70: CUMPLE | AJ70: CUMPLE | AK70: CUMPLE | AL70: CUMPLE | AM70: CUMPLE | AN70: CUMPLE | AO70: CUMPLE | AP70: CUMPLE | AQ70: CUMPLE | AR70: CUMPLE | AS70: CUMPLE | AT70: CUMPLE | AU70: CUMPLE | AV70: CUMPLE | AW70: CUMPLE | AY70: Cumple | AZ70: Cumple | BA70: Cumple | BB70: No
A71: 45860.26 | B71: Edisson Pastrana Aldana | C71: OPERACIÓN | D71: SAN FRANCISCO | E71: WPT277 | F71: 71232 | G71: DIURNA | H71: CUMPLE | I71: CUMPLE | J71: CUMPLE | K71: CUMPLE | L71: CUMPLE | M71: CUMPLE | N71: CUMPLE | O71: CUMPLE | P71: CUMPLE | Q71: CUMPLE | R71: CUMPLE | S71: CUMPLE | T71: CUMPLE | U71: CUMPLE | V71: CUMPLE | W71: CUMPLE | X71: CUMPLE | Y71: CUMPLE | Z71: CUMPLE | AA71: CUMPLE | AB71: CUMPLE | AC71: NO APLICA | AD71: NO APLICA | AE71: NO APLICA | AF71: NO APLICA | AG71: CUMPLE | AH71: CUMPLE | AI71: CUMPLE | AJ71: CUMPLE | AK71: CUMPLE | AL71: CUMPLE | AM71: CUMPLE | AN71: CUMPLE | AO71: CUMPLE | AP71: CUMPLE | AQ71: CUMPLE | AR71: CUMPLE | AS71: CUMPLE | AT71: CUMPLE | AU71: CUMPLE | AV71: CUMPLE | AW71: CUMPLE | AY71: Cumple | AZ71: Cumple | BA71: Cumple | BB71: No
A72: 45860.262 | B72: Eladio Perdomo Pérez | C72: MANTENIMIENTO (CONSORCIO SAS-CFP) | D72: DINA | E72: THP849 | F72: 130413 | G72: DIURNA | H72: CUMPLE | I72: CUMPLE | J72: CUMPLE | K72: CUMPLE | L72: CUMPLE | M72: CUMPLE | N72: CUMPLE | O72: CUMPLE | P72: CUMPLE | Q72: CUMPLE | R72: CUMPLE | S72: CUMPLE | T72: CUMPLE | U72: CUMPLE | V72: CUMPLE | W72: CUMPLE | X72: CUMPLE | Y72: CUMPLE | Z72: CUMPLE | AA72: CUMPLE | AB72: CUMPLE | AC72: NO APLICA | AD72: NO APLICA | AE72: NO APLICA | AF72: NO APLICA | AG72: CUMPLE | AH72: CUMPLE | AI72: CUMPLE | AJ72: CUMPLE | AK72: CUMPLE | AL72: CUMPLE | AM72: CUMPLE | AN72: CUMPLE | AO72: CUMPLE | AP72: CUMPLE | AQ72: CUMPLE | AR72: CUMPLE | AS72: CUMPLE | AT72: CUMPLE | AU72: CUMPLE | AV72: CUMPLE | AW72: CUMPLE | AY72: Cumple | AZ72: Cumple | BA72: Cumple | BB72: No
A73: 45860.268 | B73: Diego Andres Ramírez Mosquera | C73: OPERACIÓN | D73: DINA | E73: Eqq657 | F73: 221242 | G73: DIURNA | H73: CUMPLE | I73: CUMPLE | J73: CUMPLE | K73: CUMPLE | L73: CUMPLE | M73: CUMPLE | N73: CUMPLE | O73: CUMPLE | P73: CUMPLE | Q73: CUMPLE | R73: CUMPLE | S73: CUMPLE | T73: CUMPLE | U73: CUMPLE | V73: CUMPLE | W73: CUMPLE | X73: CUMPLE | Y73: CUMPLE | Z73: CUMPLE | AA73: CUMPLE | AB73: CUMPLE | AC73: CUMPLE | AD73: CUMPLE | AE73: CUMPLE | AF73: CUMPLE | AG73: CUMPLE | AH73: CUMPLE | AI73: CUMPLE | AJ73: CUMPLE | AK73: CUMPLE | AL73: CUMPLE | AM73: CUMPLE | AN73: CUMPLE | AO73: CUMPLE | AP73: CUMPLE | AQ73: CUMPLE | AR73: CUMPLE | AS73: CUMPLE | AT73: CUMPLE | AU73: CUMPLE | AV73: CUMPLE | AW73: CUMPLE | AY73: Cumple | AZ73: Cumple | BA73: Cumple | BB73: No
A74: 45860.27 | B74: Hernan david menza | C74: OPERACIÓN | D74: YAGUARA | E74: Lpz 104 | F74: 37292 | G74: DIURNA | H74: CUMPLE | I74: CUMPLE | J74: CUMPLE | K74: CUMPLE | L74: CUMPLE | M74: CUMPLE | N74: CUMPLE | O74: CUMPLE | P74: CUMPLE | Q74: CUMPLE | R74: CUMPLE | S74: CUMPLE | T74: CUMPLE | U74: NO CUMPLE | V74: CUMPLE | W74: CUMPLE | X74: CUMPLE | Y74: CUMPLE | Z74: CUMPLE | AA74: CUMPLE | AB74: CUMPLE | AC74: CUMPLE | AD74: CUMPLE | AE74: CUMPLE | AF74: CUMPLE | AG74: CUMPLE | AH74: CUMPLE | AI74: CUMPLE | AJ74: CUMPLE | AK74: CUMPLE | AL74: CUMPLE | AM74: CUMPLE | AN74: CUMPLE | AO74: CUMPLE | AP74: CUMPLE | AQ74: CUMPLE | AR74: CUMPLE | AS74: CUMPLE | AT74: CUMPLE | AU74: CUMPLE | AV74: CUMPLE | AW74: CUMPLE | AY74: Cumple | AZ74: Cumple | BA74: Cumple | BB74: No
A75: 45860.285 | B75: YILBER LOSADA | C75: OPERACIÓN | D75: DINA | E75: WPT278 | F75: 137695 | G75: DIURNA | H75: CUMPLE | I75: CUMPLE | J75: CUMPLE | K75: CUMPLE | L75: CUMPLE | M75: CUMPLE | N75: CUMPLE | O75: CUMPLE | P75: CUMPLE | Q75: CUMPLE | R75: CUMPLE | S75: CUMPLE | T75: CUMPLE | U75: CUMPLE | V75: CUMPLE | W75: CUMPLE | X75: CUMPLE | Y75: CUMPLE | Z75: CUMPLE | AA75: CUMPLE | AB75: CUMPLE | AC75: NO APLICA | AD75: NO APLICA | AE75: NO APLICA | AF75: NO APLICA | AG75: CUMPLE | AH75: CUMPLE | AI75: CUMPLE | AJ75: CUMPLE | AK75: CUMPLE | AL75: CUMPLE | AM75: CUMPLE | AN75: CUMPLE | AO75: CUMPLE | AP75: CUMPLE | AQ75: CUMPLE | AR75: CUMPLE | AS75: CUMPLE | AT75: CUMPLE | AU75: CUMPLE | AV75: CUMPLE | AW75: CUMPLE | AX75: Cambio de aceite Actual 137595 Prox 136913 | AY75: Cumple | AZ75: Cumple | BA75: Cumple | BB75: No
A76: 45860.298 | B76: Gerardo ariza | C76: MANTENIMIENTO (CONSORCIO SAS-CFP) | D76: DINA | E76: EQZ742 | F76: 96766 | G76: DIURNA | H76: CUMPLE | I76: CUMPLE | J76: CUMPLE | K76: CUMPLE | L76: CUMPLE | M76: CUMPLE | N76: NO CUMPLE | O76: CUMPLE | P76: CUMPLE | Q76: CUMPLE | R76: CUMPLE | S76: CUMPLE | T76: CUMPLE | U76: CUMPLE | V76: CUMPLE | W76: CUMPLE | X76: CUMPLE | Y76: CUMPLE | Z76: CUMPLE | AA76: CUMPLE | AB76: CUMPLE | AC76: CUMPLE | AD76: CUMPLE | AE76: CUMPLE | AF76: NO APLICA | AG76: CUMPLE | AH76: CUMPLE | AI76: CUMPLE | AJ76: CUMPLE | AK76: CUMPLE | AL76: CUMPLE | AM76: CUMPLE | AN76: CUMPLE | AO76: CUMPLE | AP76: CUMPLE | AQ76: CUMPLE | AR76: CUMPLE | AS76: CUMPLE | AT76: CUMPLE | AU76: CUMPLE | AV76: CUMPLE | AW76: CUMPLE | AX76: Pendiente cambio panorámico, suministrar herramienta básicas, llantas traceras pequeñas, vías en mal estado, Pendiente cambio sensor de combustible, lavado general, Pendiente aval | AY76: Cumple | AZ76: Cumple | BA76: Cumple | BB76: No
A77: 45860.299 | B77: Michelle Aroca Medina | C77: OPERACIÓN | D77: SAN FRANCISCO | E77: WPT 243 | F77: 96107 | G77: DIURNA | H77: CUMPLE | I77: CUMPLE | J77: CUMPLE | K77: CUMPLE | L77: CUMPLE | M77: CUMPLE | N77: CUMPLE | O77: CUMPLE | P77: CUMPLE | Q77: CUMPLE | R77: CUMPLE | S77: CUMPLE | T77: CUMPLE | U77: CUMPLE | V77: CUMPLE | W77: CUMPLE | X77: CUMPLE | Y77: CUMPLE | Z77: CUMPLE | AA77: CUMPLE | AB77: CUMPLE | AC77: NO APLICA | AD77: NO APLICA | AE77: NO APLICA | AF77: NO APLICA | AG77: CUMPLE | AH77: CUMPLE | AI77: CUMPLE | AJ77: CUMPLE | AK77: CUMPLE | AL77: CUMPLE | AM77: CUMPLE | AN77: CUMPLE | AO77: CUMPLE | AP77: CUMPLE | AQ77: CUMPLE | AR77: CUMPLE | AS77: CUMPLE | AT77: CUMPLE | AU77: CUMPLE | AV77: CUMPLE | AW77: CUMPLE | AX77: Radio malo Falta de alineación | AY77: Cumple | AZ77: Cumple | BA77: Cumple | BB77: No
A78: 45860.3 | B78: Aldemar González Lasso | C78: MANTENIMIENTO (CONSORCIO SAS-CFP) | D78: SAN FRANCISCO | E78: THS530 | F78: 55516 | G78: DIURNA | H78: CUMPLE | I78: CUMPLE | J78: CUMPLE | K78: CUMPLE | L78: CUMPLE | M78: CUMPLE | N78: CUMPLE | O78: CUMPLE | P78: CUMPLE | Q78: CUMPLE | R78: CUMPLE | S78: CUMPLE | T78: CUMPLE | U78: CUMPLE | V78: CUMPLE | W78: CUMPLE | X78: CUMPLE | Y78: CUMPLE | Z78: CUMPLE | AA78: CUMPLE | AB78: CUMPLE | AC78: NO APLICA | AD78: NO APLICA | AE78: NO APLICA | AF78: NO APLICA | AG78: CUMPLE | AH78: CUMPLE | AI78: CUMPLE | AJ78: CUMPLE | AK78: CUMPLE | AL78: CUMPLE | AM78: CUMPLE | AN78: CUMPLE | AO78: CUMPLE | AP78: CUMPLE | AQ78: CUMPLE | AR78: CUMPLE | AS78: CUMPLE | AT78: CUMPLE | AU78: CUMPLE | AV78: CUMPLE | AW78: CUMPLE | AX78: Sin novedad | AY78: Cumple | AZ78: Cumple | BA78: Cumple | BB78: No
A79: 45860.301 | B79: Jhoan Tamayo Perdomo | C79: OPERACIÓN | D79: YAGUARA | E79: THS412 | F79: 37982 | G79: NO APLICA | H79: CUMPLE | I79: CUMPLE | J79: CUMPLE | K79: CUMPLE | L79: CUMPLE | M79: CUMPLE | N79: CUMPLE | O79: CUMPLE | P79: CUMPLE | Q79: NO CUMPLE | R79: CUMPLE | S79: CUMPLE | T79: CUMPLE | U79: CUMPLE | V79: CUMPLE | W79: CUMPLE | X79: CUMPLE | Y79: CUMPLE | Z79: CUMPLE | AA79: CUMPLE | AB79: CUMPLE | AC79: NO APLICA | AD79: NO APLICA | AE79: NO APLICA | AF79: NO APLICA | AG79: CUMPLE | AH79: CUMPLE | AI79: CUMPLE | AJ79: CUMPLE | AK79: CUMPLE | AL79: CUMPLE | AM79: CUMPLE | AN79: CUMPLE | AO79: CUMPLE | AP79: CUMPLE | AQ79: CUMPLE | AR79: CUMPLE | AS79: CUMPLE | AT79: CUMPLE | AU79: CUMPLE | AV79: CUMPLE | AW79: CUMPLE | AY79: Cumple | AZ79: Cumple | BA79: Cumple | BB79: No
A80: 45860.312 | B80: Fdo castillo | C80: MANTENIMIENTO (CONSORCIO SAS-CFP) | D80: DINA | E80: Ths 082 | F80: 174871 | G80: DIURNA | H80: CUMPLE | I80: CUMPLE | J80: CUMPLE | K80: CUMPLE | L80: CUMPLE | M80: CUMPLE | N80: CUMPLE | O80: CUMPLE | P80: CUMPLE | Q80: CUMPLE | R80: CUMPLE | S80: CUMPLE | T80: CUMPLE | U80: CUMPLE | V80: CUMPLE | W80: CUMPLE | X80: CUMPLE | Y80: CUMPLE | Z80: CUMPLE | AA80: CUMPLE | AB80: CUMPLE | AC80: CUMPLE | AD80: CUMPLE | AE80: CUMPLE | AF80: CUMPLE | AG80: CUMPLE | AH80: CUMPLE | AI80: CUMPLE | AJ80: CUMPLE | AK80: CUMPLE | AL80: CUMPLE | AM80: CUMPLE | AN80: CUMPLE | AO80: CUMPLE | AP80: CUMPLE | AQ80: CUMPLE | AR80: CUMPLE | AS80: CUMPLE | AT80: CUMPLE | AU80: CUMPLE | AV80: CUMPLE | AW80: CUMPLE | AY80: Cumple | AZ80: Cumple | BA80: Cumple | BB80: No
A81: 45860.315 | B81: Jorge Lasso diaz | C81: OPERACIÓN | D81: DINA | E81: THQ136 | F81: 71450 | G81: DIURNA | H81: CUMPLE | I81: CUMPLE | J81: CUMPLE | K81: CUMPLE | L81: CUMPLE | M81: CUMPLE | N81: CUMPLE | O81: CUMPLE | P81: CUMPLE | Q81: CUMPLE | R81: CUMPLE | S81: CUMPLE | T81: CUMPLE | U81: CUMPLE | V81: CUMPLE | W81: CUMPLE | X81: CUMPLE | Y81: CUMPLE | Z81: CUMPLE | AA81: CUMPLE | AB81: CUMPLE | AC81: NO APLICA | AD81: NO APLICA | AE81: NO APLICA | AF81: NO APLICA | AG81: CUMPLE | AH81: CUMPLE | AI81: CUMPLE | AJ81: CUMPLE | AK81: CUMPLE | AL81: CUMPLE | AM81: CUMPLE | AN81: CUMPLE | AO81: CUMPLE | AP81: CUMPLE | AQ81: CUMPLE | AR81: CUMPLE | AS81: CUMPLE | AT81: CUMPLE | AU81: CUMPLE | AV81: CUMPLE | AW81: CUMPLE | AY81: Cumple | AZ81: Cumple | BA81: Cumple | BB81: No
A82: 45860.32 | B82: Jonh edinsson Charry Villarreal | C82: OPERACIÓN | D82: DINA | E82: THQ-137 | F82: 83946 | G82: DIURNA | H82: CUMPLE | I82: CUMPLE | J82: CUMPLE | K82: CUMPLE | L82: CUMPLE | M82: CUMPLE | N82: CUMPLE | O82: CUMPLE | P82: CUMPLE | Q82: CUMPLE | R82: CUMPLE | S82: CUMPLE | T82: CUMPLE | U82: CUMPLE | V82: CUMPLE | W82: CUMPLE | X82: NO CUMPLE | Y82: CUMPLE | Z82: CUMPLE | AA82: CUMPLE | AB82: CUMPLE | AC82: NO APLICA | AD82: NO APLICA | AE82: NO APLICA | AF82: NO APLICA | AG82: CUMPLE | AH82: CUMPLE | AI82: CUMPLE | AJ82: CUMPLE | AK82: CUMPLE | AL82: CUMPLE | AM82: CUMPLE | AN82: CUMPLE | AO82: CUMPLE | AP82: NO CUMPLE | AQ82: CUMPLE | AR82: CUMPLE | AS82: CUMPLE | AT82: CUMPLE | AU82: CUMPLE | AV82: CUMPLE | AW82: CUMPLE | AY82: Cumple | AZ82: Cumple | BA82: Cumple | BB82: No
A83: 45860.322 | B83: Jorge Mosquera | C83: OPERACIÓN | D83: TELLO | E83: NTQ 466 | F83: 5439 | G83: DIURNA | H83: CUMPLE | I83: CUMPLE | J83: CUMPLE | K83: CUMPLE | L83: CUMPLE | M83: CUMPLE | N83: CUMPLE | O83: CUMPLE | P83: CUMPLE | Q83: CUMPLE | R83: CUMPLE | S83: CUMPLE | T83: CUMPLE | U83: CUMPLE | V83: CUMPLE | W83: CUMPLE | X83: CUMPLE | Y83: CUMPLE | Z83: CUMPLE | AA83: CUMPLE | AB83: CUMPLE | AC83: CUMPLE | AD83: CUMPLE | AE83: CUMPLE | AF83: CUMPLE | AG83: CUMPLE | AH83: CUMPLE | AI83: CUMPLE | AJ83: CUMPLE | AK83: CUMPLE | AL83: CUMPLE | AM83: CUMPLE | AN83: CUMPLE | AO83: CUMPLE | AP83: CUMPLE | AQ83: CUMPLE | AR83: CUMPLE | AS83: CUMPLE | AT83: CUMPLE | AU83: CUMPLE | AV83: CUMPLE | AW83: CUMPLE | AY83: Cumple | AZ83: Cumple | BA83: Cumple | BB83: No
A84: 45860.328 | B84: Leonardo charry charry | C84: OPERACIÓN | D84: DINA | E84: WPT247 | F84: 106764 | G84: DIURNA | H84: CUMPLE | I84: CUMPLE | J84: CUMPLE | K84: CUMPLE | L84: CUMPLE | M84: CUMPLE | N84: CUMPLE | O84: CUMPLE | P84: CUMPLE | Q84: CUMPLE | R84: CUMPLE | S84: CUMPLE | T84: CUMPLE | U84: CUMPLE | V84: CUMPLE | W84: CUMPLE | X84: CUMPLE | Y84: CUMPLE | Z84: CUMPLE | AA84: CUMPLE | AB84: CUMPLE | AC84: NO APLICA | AD84: NO APLICA | AE84: NO APLICA | AF84: NO APLICA | AG84: CUMPLE | AH84: CUMPLE | AI84: CUMPLE | AJ84: CUMPLE | AK84: CUMPLE | AL84: CUMPLE | AM84: CUMPLE | AN84: CUMPLE | AO84: CUMPLE | AP84: CUMPLE | AQ84: CUMPLE | AR84: CUMPLE | AS84: CUMPLE | AT84: CUMPLE | AU84: CUMPLE | AV84: CUMPLE | AW84: CUMPLE | AX84: La manija de la puerta trasera está mala, esta dañado tambien el sistema del limpiaparabrisas | AY84: Cumple | AZ84: Cumple | BA84: Cumple | BB84: No
A85: 45860.331 | B85: Juan Diego Cabrera | C85: OPERACIÓN | D85: SAN FRANCISCO | E85: THQ 021 | F85: 91760 | G85: DIURNA | H85: CUMPLE | I85: CUMPLE | J85: CUMPLE | K85: CUMPLE | L85: CUMPLE | M85: CUMPLE | N85: CUMPLE | O85: CUMPLE | P85: CUMPLE | Q85: CUMPLE | R85: CUMPLE | S85: CUMPLE | T85: CUMPLE | U85: CUMPLE | V85: CUMPLE | W85: CUMPLE | X85: CUMPLE | Y85: CUMPLE | Z85: CUMPLE | AA85: CUMPLE | AB85: CUMPLE | AC85: NO APLICA | AD85: NO APLICA | AE85: NO APLICA | AF85: NO APLICA | AG85: CUMPLE | AH85: CUMPLE | AI85: CUMPLE | AJ85: CUMPLE | AK85: CUMPLE | AL85: CUMPLE | AM85: CUMPLE | AN85: CUMPLE | AO85: CUMPLE | AP85: CUMPLE | AQ85: CUMPLE | AR85: CUMPLE | AS85: CUMPLE | AT85: CUMPLE | AU85: CUMPLE | AV85: CUMPLE | AW85: CUMPLE | AY85: Cumple | AZ85: Cumple | BA85: Cumple | BB85: No
A86: 45860.349 | B86: DEYMER BORRERO MOSQUERA | C86: OPERACIÓN | D86: TELLO | E86: WPT241 | F86: 60694 | G86: DIURNA | H86: CUMPLE | I86: CUMPLE | J86: CUMPLE | K86: CUMPLE | L86: CUMPLE | M86: CUMPLE | N86: CUMPLE | O86: CUMPLE | P86: CUMPLE | Q86: CUMPLE | R86: CUMPLE | S86: CUMPLE | T86: CUMPLE | U86: CUMPLE | V86: CUMPLE | W86: CUMPLE | X86: CUMPLE | Y86: CUMPLE | Z86: CUMPLE | AA86: CUMPLE | AB86: CUMPLE | AC86: NO APLICA | AD86: NO APLICA | AE86: NO APLICA | AF86: NO APLICA | AG86: CUMPLE | AH86: CUMPLE | AI86: CUMPLE | AJ86: CUMPLE | AK86: CUMPLE | AL86: CUMPLE | AM86: CUMPLE | AN86: CUMPLE | AO86: CUMPLE | AP86: CUMPLE | AQ86: CUMPLE | AR86: CUMPLE | AS86: CUMPLE | AT86: CUMPLE | AU86: CUMPLE | AV86: CUMPLE | AW86: CUMPLE | AY86: Cumple | AZ86: Cumple | BA86: Cumple | BB86: No
A87: 45860.366 | B87: Wilver Collazos Quiroga | C87: MANTENIMIENTO (CONSORCIO SAS-CFP) | D87: DINA | E87: WPT 239 | F87: 104309 | G87: DIURNA | H87: CUMPLE | I87: CUMPLE | J87: CUMPLE | K87: CUMPLE | L87: CUMPLE | M87: CUMPLE | N87: NO CUMPLE | O87: CUMPLE | P87: CUMPLE | Q87: CUMPLE | R87: CUMPLE | S87: CUMPLE | T87: CUMPLE | U87: CUMPLE | V87: CUMPLE | W87: CUMPLE | X87: CUMPLE | Y87: CUMPLE | Z87: CUMPLE | AA87: CUMPLE | AB87: CUMPLE | AC87: NO APLICA | AD87: NO APLICA | AE87: NO APLICA | AF87: NO APLICA | AG87: CUMPLE | AH87: CUMPLE | AI87: CUMPLE | AJ87: CUMPLE | AK87: CUMPLE | AL87: CUMPLE | AM87: CUMPLE | AN87: CUMPLE | AO87: CUMPLE | AP87: CUMPLE | AQ87: CUMPLE | AR87: CUMPLE | AS87: CUMPLE | AT87: CUMPLE | AU87: CUMPLE | AV87: CUMPLE | AW87: CUMPLE | AX87: Parabrisas fisurado, se requiere cambio de tuercas de llantas delnteras, rayones leves en cabina por maleza hacía las vías de algunos pozos, el vehículo se le está filtrando el agua lluvia por el vidrio trasero y el caucho, vías en mal estado y pueden causar daños a partes del vehículo, unidad lateral izquierdo fisurada ya hace más de dos años | AY87: Cumple | AZ87: Cumple | BA87: Cumple | BB87: No
A88: 45860.497 | B88: Sergio Barreto | C88: OPERACIÓN | D88: TELLO | E88: THS658 | F88: 1062 | G88: DIURNA | H88: CUMPLE | I88: CUMPLE | J88: CUMPLE | K88: CUMPLE | L88: CUMPLE | M88: CUMPLE | N88: CUMPLE | O88: CUMPLE | P88: CUMPLE | Q88: CUMPLE | R88: CUMPLE | S88: CUMPLE | T88: CUMPLE | U88: CUMPLE | V88: CUMPLE | W88: CUMPLE | X88: CUMPLE | Y88: CUMPLE | Z88: CUMPLE | AA88: CUMPLE | AB88: CUMPLE | AC88: NO APLICA | AD88: NO APLICA | AE88: NO APLICA | AF88: NO APLICA | AG88: CUMPLE | AH88: CUMPLE | AI88: CUMPLE | AJ88: CUMPLE | AK88: CUMPLE | AL88: CUMPLE | AM88: CUMPLE | AN88: CUMPLE | AO88: CUMPLE | AP88: CUMPLE | AQ88: CUMPLE | AR88: CUMPLE | AS88: CUMPLE | AT88: CUMPLE | AU88: CUMPLE | AV88: CUMPLE | AW88: CUMPLE | AY88: Cumple | AZ88: Cumple | BA88: Cumple | BB88: No
A89: 45860.621 | B89: José vicente alvarez | C89: OPERACIÓN | D89: DINA | E89: WPT246 | F89: 90380 | G89: DIURNA | H89: CUMPLE | I89: CUMPLE | J89: CUMPLE | K89: CUMPLE | L89: CUMPLE | M89: CUMPLE | N89: CUMPLE | O89: CUMPLE | P89: CUMPLE | Q89: CUMPLE | R89: CUMPLE | S89: CUMPLE | T89: CUMPLE | U89: CUMPLE | V89: CUMPLE | W89: CUMPLE | X89: CUMPLE | Y89: CUMPLE | Z89: CUMPLE | AA89: CUMPLE | AB89: CUMPLE | AC89: NO APLICA | AD89: NO APLICA | AE89: NO APLICA | AF89: NO APLICA | AG89: CUMPLE | AH89: CUMPLE | AI89: CUMPLE | AJ89: CUMPLE | AK89: CUMPLE | AL89: CUMPLE | AM89: CUMPLE | AN89: CUMPLE | AO89: CUMPLE | AP89: CUMPLE | AQ89: CUMPLE | AR89: CUMPLE | AS89: CUMPLE | AT89: CUMPLE | AU89: CUMPLE | AV89: CUMPLE | AW89: CUMPLE | AX89: Sin vidrio en lateral izquierdo ,falta de ajustes en puertas , carroceria en malas condiciones, no tiene pitó de reversa , antivolco doblado | AY89: Cumple | AZ89: Cumple | BA89: Cumple | BB89: No
A90: 45860.708 | B90: Jose Miller Escobar Tello | C90: OPERACIÓN | D90: TELLO | E90: Lhw 521 | F90: 86952 | G90: NOCTURNA | H90: CUMPLE | I90: CUMPLE | J90: CUMPLE | K90: CUMPLE | L90: CUMPLE | M90: CUMPLE | N90: CUMPLE | O90: CUMPLE | P90: CUMPLE | Q90: CUMPLE | R90: CUMPLE | S90: CUMPLE | T90: CUMPLE | U90: CUMPLE | V90: CUMPLE | W90: CUMPLE | X90: CUMPLE | Y90: CUMPLE | Z90: CUMPLE | AA90: CUMPLE | AB90: CUMPLE | AC90: CUMPLE | AD90: CUMPLE | AE90: CUMPLE | AF90: CUMPLE | AG90: CUMPLE | AH90: CUMPLE | AI90: CUMPLE | AJ90: CUMPLE | AK90: CUMPLE | AL90: CUMPLE | AM90: CUMPLE | AN90: CUMPLE | AO90: CUMPLE | AP90: CUMPLE | AQ90: CUMPLE | AR90: CUMPLE | AS90: CUMPLE | AT90: CUMPLE | AU90: CUMPLE | AV90: CUMPLE | AW90: CUMPLE | AY90: Cumple | AZ90: Cumple | BA90: Cumple | BB90: No
A91: 45861.241 | B91: DEYMER BORRERO MOSQUERA | C91: OPERACIÓN | D91: TELLO | E91: WPT241 | F91: 60724 | G91: DIURNA | H91: CUMPLE | I91: CUMPLE | J91: CUMPLE | K91: CUMPLE | L91: CUMPLE | M91: CUMPLE | N91: CUMPLE | O91: CUMPLE | P91: CUMPLE | Q91: CUMPLE | R91: CUMPLE | S91: CUMPLE | T91: CUMPLE | U91: CUMPLE | V91: CUMPLE | W91: CUMPLE | X91: CUMPLE | Y91: CUMPLE | Z91: CUMPLE | AA91: CUMPLE | AB91: CUMPLE | AC91: NO APLICA | AD91: NO APLICA | AE91: NO APLICA | AF91: NO APLICA | AG91: CUMPLE | AH91: CUMPLE | AI91: CUMPLE | AJ91: CUMPLE | AK91: CUMPLE | AL91: CUMPLE | AM91: CUMPLE | AN91: CUMPLE | AO91: CUMPLE | AP91: CUMPLE | AQ91: CUMPLE | AR91: CUMPLE | AS91: CUMPLE | AT91: CUMPLE | AU91: CUMPLE | AV91: CUMPLE | AW91: CUMPLE | AY91: Cumple | AZ91: Cumple | BA91: Cumple | BB91: No
A92: 45861.245 | B92: José Ramírez | C92: OPERACIÓN | D92: DINA | E92: EQQ657 | F92: 221312 | G92: DIURNA | H92: CUMPLE | I92: CUMPLE | J92: CUMPLE | K92: CUMPLE | L92: CUMPLE | M92: CUMPLE | N92: CUMPLE | O92: CUMPLE | P92: CUMPLE | Q92: CUMPLE | R92: CUMPLE | S92: CUMPLE | T92: CUMPLE | U92: CUMPLE | V92: CUMPLE | W92: CUMPLE | X92: CUMPLE | Y92: CUMPLE | Z92: CUMPLE | AA92: CUMPLE | AB92: CUMPLE | AC92: CUMPLE | AD92: CUMPLE | AE92: CUMPLE | AF92: CUMPLE | AG92: CUMPLE | AH92: CUMPLE | AI92: CUMPLE | AJ92: CUMPLE | AK92: CUMPLE | AL92: CUMPLE | AM92: CUMPLE | AN92: CUMPLE | AO92: CUMPLE | AP92: CUMPLE | AQ92: CUMPLE | AR92: CUMPLE | AS92: CUMPLE | AT92: CUMPLE | AU92: CUMPLE | AV92: CUMPLE | AW92: CUMPLE | AY92: Cumple | AZ92: Cumple | BA92: Cumple | BB92: No
A93: 45861.258 | B93: EDISSON PASTRANA ALDANA | C93: OPERACIÓN | D93: SAN FRANCISCO | E93: WPT 277 | F93: 71320 | G93: DIURNA | H93: CUMPLE | I93: CUMPLE | J93: CUMPLE | K93: CUMPLE | L93: CUMPLE | M93: CUMPLE | N93: CUMPLE | O93: CUMPLE | P93: CUMPLE | Q93: CUMPLE | R93: CUMPLE | S93: CUMPLE | T93: CUMPLE | U93: CUMPLE | V93: CUMPLE | W93: CUMPLE | X93: CUMPLE | Y93: CUMPLE | Z93: CUMPLE | AA93: CUMPLE | AB93: CUMPLE | AC93: NO APLICA | AD93: NO APLICA | AE93: NO APLICA | AF93: NO APLICA | AG93: CUMPLE | AH93: CUMPLE | AI93: CUMPLE | AJ93: CUMPLE | AK93: CUMPLE | AL93: CUMPLE | AM93: CUMPLE | AN93: CUMPLE | AO93: CUMPLE | AP93: CUMPLE | AQ93: CUMPLE | AR93: CUMPLE | AS93: CUMPLE | AT93: CUMPLE | AU93: CUMPLE | AV93: CUMPLE | AW93: CUMPLE | AY93: Cumple | AZ93: Cumple | BA93: Cumple | BB93: No
A94: 45861.259 | B94: Jorge Mosquera | C94: OPERACIÓN | D94: TELLO | E94: NtQ 466 | F94: 5468 | G94: DIURNA | H94: CUMPLE | I94: CUMPLE | J94: CUMPLE | K94: CUMPLE | L94: CUMPLE | M94: CUMPLE | N94: CUMPLE | O94: CUMPLE | P94: CUMPLE | Q94: CUMPLE | R94: CUMPLE | S94: CUMPLE | T94: CUMPLE | U94: CUMPLE | V94: CUMPLE | W94: CUMPLE | X94: CUMPLE | Y94: CUMPLE | Z94: CUMPLE | AA94: CUMPLE | AB94: CUMPLE | AC94: CUMPLE | AD94: CUMPLE | AE94: CUMPLE | AF94: CUMPLE | AG94: CUMPLE | AH94: CUMPLE | AI94: CUMPLE | AJ94: CUMPLE | AK94: CUMPLE | AL94: CUMPLE | AM94: CUMPLE | AN94: CUMPLE | AO94: CUMPLE | AP94: CUMPLE | AQ94: CUMPLE | AR94: CUMPLE | AS94: CUMPLE | AT94: CUMPLE | AU94: CUMPLE | AV94: CUMPLE | AW94: CUMPLE | AY94: Cumple | AZ94: Cumple | BA94: Cumple | BB94: No
A95: 45861.27 | B95: Juan Diego Cabrera | C95: OPERACIÓN | D95: SAN FRANCISCO | E95: THQ 021 | F95: 91841 | G95: DIURNA | H95: CUMPLE | I95: CUMPLE | J95: CUMPLE | K95: CUMPLE | L95: CUMPLE | M95: CUMPLE | N95: CUMPLE | O95: CUMPLE | P95: CUMPLE | Q95: CUMPLE | R95: CUMPLE | S95: CUMPLE | T95: CUMPLE | U95: CUMPLE | V95: CUMPLE | W95: CUMPLE | X95: CUMPLE | Y95: CUMPLE | Z95: CUMPLE | AA95: CUMPLE | AB95: CUMPLE | AC95: NO APLICA | AD95: NO APLICA | AE95: NO APLICA | AF95: NO APLICA | AG95: CUMPLE | AH95: CUMPLE | AI95: CUMPLE | AJ95: CUMPLE | AK95: CUMPLE | AL95: CUMPLE | AM95: CUMPLE | AN95: CUMPLE | AO95: CUMPLE | AP95: CUMPLE | AQ95: CUMPLE | AR95: CUMPLE | AS95: CUMPLE | AT95: CUMPLE | AU95: CUMPLE | AV95: CUMPLE | AW95: CUMPLE | AY95: Cumple | AZ95: Cumple | BA95: Cumple | BB95: No
A96: 45861.272 | B96: Eladio Perdomo Pérez | C96: MANTENIMIENTO (CONSORCIO SAS-CFP) | D96: DINA | E96: THP849 | F96: 130487 | G96: DIURNA | H96: CUMPLE | I96: CUMPLE | J96: CUMPLE | K96: CUMPLE | L96: CUMPLE | M96: CUMPLE | N96: CUMPLE | O96: CUMPLE | P96: CUMPLE | Q96: CUMPLE | R96: CUMPLE | S96: CUMPLE | T96: CUMPLE | U96: CUMPLE | V96: CUMPLE | W96: CUMPLE | X96: CUMPLE | Y96: CUMPLE | Z96: CUMPLE | AA96: CUMPLE | AB96: CUMPLE | AC96: NO APLICA | AD96: NO APLICA | AE96: NO APLICA | AF96: NO APLICA | AG96: CUMPLE | AH96: CUMPLE | AI96: CUMPLE | AJ96: CUMPLE | AK96: CUMPLE | AL96: CUMPLE | AM96: CUMPLE | AN96: CUMPLE | AO96: CUMPLE | AP96: CUMPLE | AQ96: CUMPLE | AR96: CUMPLE | AS96: CUMPLE | AT96: CUMPLE | AU96: CUMPLE | AV96: CUMPLE | AW96: CUMPLE | AY96: Cumple | AZ96: Cumple | BA96: Cumple | BB96: No
A97: 45861.295 | B97: Jonh edinsson Charry Villarreal | C97: OPERACIÓN | D97: DINA | E97: THQ-137 | F97: 83985 | G97: DIURNA | H97: CUMPLE | I97: CUMPLE | J97: CUMPLE | K97: CUMPLE | L97: CUMPLE | M97: CUMPLE | N97: CUMPLE | O97: CUMPLE | P97: CUMPLE | Q97: CUMPLE | R97: CUMPLE | S97: CUMPLE | T97: CUMPLE | U97: CUMPLE | V97: CUMPLE | W97: CUMPLE | X97: NO CUMPLE | Y97: CUMPLE | Z97: CUMPLE | AA97: CUMPLE | AB97: CUMPLE | AC97: NO APLICA | AD97: NO APLICA | AE97: NO APLICA | AF97: NO APLICA | AG97: CUMPLE | AH97: CUMPLE | AI97: CUMPLE | AJ97: CUMPLE | AK97: CUMPLE | AL97: CUMPLE | AM97: CUMPLE | AN97: CUMPLE | AO97: CUMPLE | AP97: NO CUMPLE | AQ97: CUMPLE | AR97: CUMPLE | AS97: CUMPLE | AT97: CUMPLE | AU97: CUMPLE | AV97: CUMPLE | AW97: CUMPLE | AY97: Cumple | AZ97: No cumple | BA97: Cumple | BB97: No
A98: 45861.301 | B98: Michel aroca Medina | C98: OPERACIÓN | D98: SAN FRANCISCO | E98: WPT 243 | F98: 96155 | G98: DIURNA | H98: CUMPLE | I98: CUMPLE | J98: CUMPLE | K98: CUMPLE | L98: CUMPLE | M98: CUMPLE | N98: CUMPLE | O98: CUMPLE | P98: CUMPLE | Q98: CUMPLE | R98: CUMPLE | S98: CUMPLE | T98: CUMPLE | U98: CUMPLE | V98: CUMPLE | W98: CUMPLE | X98: CUMPLE | Y98: CUMPLE | Z98: CUMPLE | AA98: CUMPLE | AB98: CUMPLE | AC98: NO APLICA | AD98: NO APLICA | AE98: NO APLICA | AF98: NO APLICA | AG98: CUMPLE | AH98: CUMPLE | AI98: CUMPLE | AJ98: CUMPLE | AK98: CUMPLE | AL98: CUMPLE | AM98: CUMPLE | AN98: CUMPLE | AO98: CUMPLE | AP98: CUMPLE | AQ98: CUMPLE | AR98: CUMPLE | AS98: CUMPLE | AT98: CUMPLE | AU98: CUMPLE | AV98: CUMPLE | AW98: CUMPLE | AX98: Vehículo bajarlo a mantenimiento Radio malo Suspensión mala | AY98: Cumple | AZ98: Cumple | BA98: Cumple | BB98: No
A99: 45861.309 | B99: Lino Arturo Jovel Ardila | C99: OPERACIÓN | D99: YAGUARA | E99: LPZ 104 | F99: 37332 | G99: DIURNA | H99: CUMPLE | I99: CUMPLE | J99: CUMPLE | K99: CUMPLE | L99: CUMPLE | M99: CUMPLE | N99: CUMPLE | O99: CUMPLE | P99: CUMPLE | Q99: CUMPLE | R99: CUMPLE | S99: CUMPLE | T99: CUMPLE | U99: CUMPLE | V99: CUMPLE | W99: CUMPLE | X99: CUMPLE | Y99: CUMPLE | Z99: CUMPLE | AA99: CUMPLE | AB99: CUMPLE | AC99: CUMPLE | AD99: CUMPLE | AE99: CUMPLE | AF99: CUMPLE | AG99: CUMPLE | AH99: CUMPLE | AI99: CUMPLE | AJ99: CUMPLE | AK99: CUMPLE | AL99: CUMPLE | AM99: CUMPLE | AN99: CUMPLE | AO99: CUMPLE | AP99: CUMPLE | AQ99: CUMPLE | AR99: CUMPLE | AS99: CUMPLE | AT99: CUMPLE | AU99: CUMPLE | AV99: CUMPLE | AW99: CUMPLE | AY99: Cumple | AZ99: Cumple | BA99: Cumple | BB99: No
A100: 45861.31 | B100: Leonardo charry charry | C100: OPERACIÓN | D100: DINA | E100: WPT247 | F100: 106793 | G100: DIURNA | H100: CUMPLE | I100: CUMPLE | J100: CUMPLE | K100: CUMPLE | L100: CUMPLE | M100: CUMPLE | N100: CUMPLE | O100: CUMPLE | P100: CUMPLE | Q100: CUMPLE | R100: CUMPLE | S100: CUMPLE | T100: CUMPLE | U100: CUMPLE | V100: CUMPLE | W100: CUMPLE | X100: CUMPLE | Y100: CUMPLE | Z100: CUMPLE | AA100: CUMPLE | AB100: CUMPLE | AC100: NO APLICA | AD100: NO APLICA | AE100: NO APLICA | AF100: NO APLICA | AG100: CUMPLE | AH100: CUMPLE | AI100: CUMPLE | AJ100: CUMPLE | AK100: CUMPLE | AL100: CUMPLE | AM100: CUMPLE | AN100: CUMPLE | AO100: CUMPLE | AP100: CUMPLE | AQ100: CUMPLE | AR100: CUMPLE | AS100: CUMPLE | AT100: CUMPLE | AU100: CUMPLE | AV100: CUMPLE | AW100: CUMPLE | AX100: Sistema de líquido de la plumillas no funciona, la manija de puerta trasera está mala , el día que se envió a despinchar llanta delantera se partió un espárrago al bajar la llanta. | AY100: Cumple | AZ100: Cumple | BA100: Cumple | BB100: No
...

Sheet OCTUBRE
A1: Marca temporal | B1: NOMBRE DE QUIEN REALIZA LA INSPECCIÓN | C1: CONTRATO | D1: CAMPO/COORDINACIÓN | E1: PLACA DEL VEHICULO | F1: KILOMETRAJE | G1: TURNO | H1: **Altas y bajas | I1: **Direccionales derecha e izquierda | J1: **De parqueo | K1: **De freno | L1: **De reversa y alarma de retroceso | M1: **Espejo central y espejos laterales | N1: **Vidrio frontal | O1: Presentación de orden y aseo | P1: Pito | Q1: Sistema de monitoreo GPS (Alerta sonora) | R1: **Cinturones de seguridad | S1: Puertas en buen estado | T1: Vidrios en buen estado | U1: Limpia brisas | V1: Exintor vigente | W1: Botiquín | X1: Estado general de tapicería | Y1: Indicadores (nivel de combustible, temperatura, velocímetro y aceite) | Z1: **Verificar la ausencia de objetos sueltos en la cabina que puedan distraer al conductor | AA1: **Frenos | AB1: **Freno de emergencia o de mano | AC1: **Fugas de aire (movil 100) | AD1: **Control fugas de aire (movil 100) | AE1: **Candados y Bandas (movil 100) | AF1: **Acoples para tomas eléctricas y de aire (movil 100) | AG1: **Niveles de fluidos aceite motor | AH1: **Nivel de fluido de frenos | AI1: **Nivel de fluido de dirección hidraúlica | AJ1: **Nivel de fluido refrigerante | AK1: Nivel de fluido limpia parabrisas | AL1: Estado de correas | AM1: Estado de baterías, cables, conexiones | AN1: **Llantas - Labrado (min 3mm de labrado) | AO1: **Llantas - Sin cortaduras y sin abultamientos | AP1: Llanta de repuesto | AQ1: **Copas o pernos de sujeción de las llantas | AR1: **Suspensión (terminales) | AS1: **Dirección (terminales) | AT1: Tapa de tanque de combustible en buen estado | AU1: Equipo de carretera: gato, llave de pernos, herramienta básica, triángulos o conos, bloques, chaleco, señal pare-siga | AV1: Kit ambiental | AW1: Documentación: tecnomecánica y de gases, tarjeta de propiedad, SOAT, licencia de conducción y permiso para conducir interno | AX1: OBSERVACIONES | AY1: ¿Ha dormido al menos 7 horas en las últimas 24 horas? | AZ1: ¿Se encuentra libre de síntomas de fatiga (Somnolencia, dolor de cabeza, irritabilidad)? | BA1: ¿Se siente en condiciones físicas y mentales para conducir? | BB1: ¿Ha consumido medicamentos o sustancias que afecten su estado de alerta?
A2: ='Respuestas de formulario 1'!A1153 -> 45931.257 | B2: ='Respuestas de formulario 1'!B1153 -> Diego Andres Ramírez Mosquera | C2: ='Respuestas de formulario 1'!C1153 -> OPERACIÓN | D2: ='Respuestas de formulario 1'!D1153 -> DINA | E2: ='Respuestas de formulario 1'!E1153 -> EQQ657 | F2: ='Respuestas de formulario 1'!F1153 -> 222410 | G2: ='Respuestas de formulario 1'!G1153 -> DIURNA | H2: ='Respuestas de formulario 1'!H1153 -> CUMPLE | ... BB2: ='Respuestas de formulario 1'!BB1153 -> No
A3: ='Respuestas de formulario 1'!A1154 -> 45931.261 | B3: ='Respuestas de formulario 1'!B1154 -> Arbey trujillo Castro | C3: ='Respuestas de formulario 1'!C1154 -> OPERACIÓN | D3: ='Respuestas de formulario 1'!D1154 -> YAGUARA | E3: ='Respuestas de formulario 1'!E1154 -> WCZ611 | F3: ='Respuestas de formulario 1'!F1154 -> 84975 | G3: ='Respuestas de formulario 1'!G1154 -> DIURNA | H3: ='Respuestas de formulario 1'!H1154 -> CUMPLE | ... BB3: ='Respuestas de formulario 1'!BB1154 -> No
A4: ='Respuestas de formulario 1'!A1155 -> 45931.269 | B4: ='Respuestas de formulario 1'!B1155 -> Jhoan Tamayo Perdomo | C4: ='Respuestas de formulario 1'!C1155 -> OPERACIÓN | D4: ='Respuestas de formulario 1'!D1155 -> YAGUARA | E4: ='Respuestas de formulario 1'!E1155 -> THS412 | F4: ='Respuestas de formulario 1'!F1155 -> 40144 | G4: ='Respuestas de formulario 1'!G1155 -> NO APLICA | H4: ='Respuestas de formulario 1'!H1155 -> CUMPLE | ... BB4: ='Respuestas de formulario 1'!BB1155 -> No
A5: ='Respuestas de formulario 1'!A1156 -> 45931.269 | B5: ='Respuestas de formulario 1'!B1156 -> Carlos Alberto Huepe | C5: ='Respuestas de formulario 1'!C1156 -> MANTENIMIENTO (CONSORCIO SAS-CFP) | D5: ='Respuestas de formulario 1'!D1156 -> TELLO | E5: ='Respuestas de formulario 1'!E1156 -> THS082 | F5: ='Respuestas de formulario 1'!F1156 -> 176978 | G5: ='Respuestas de formulario 1'!G1156 -> DIURNA | H5: ='Respuestas de formulario 1'!H1156 -> CUMPLE | ... BB5: ='Respuestas de formulario 1'!BB1156 -> No
A6: ='Respuestas de formulario 1'!A1157 -> 45931.283 | B6: ='Respuestas de formulario 1'!B1157 -> Jonh edinsson Charry Villarreal | C6: ='Respuestas de formulario 1'!C1157 -> OPERACIÓN | D6: ='Respuestas de formulario 1'!D1157 -> DINA | E6: ='Respuestas de formulario 1'!E1157 -> THQ137 | F6: ='Respuestas de formulario 1'!F1157 -> 86625 | G6: ='Respuestas de formulario 1'!G1157 -> DIURNA | H6: ='Respuestas de formulario 1'!H1157 -> CUMPLE | ... BB6: ='Respuestas de formulario 1'!BB1157 -> No
A7: ='Respuestas de formulario 1'!A1158 -> 45931.288 | B7: ='Respuestas de formulario 1'!B1158 -> Eladio Perdomo Pérez | C7: ='Respuestas de formulario 1'!C1158 -> MANTENIMIENTO (CONSORCIO SAS-CFP) | D7: ='Respuestas de formulario 1'!D1158 -> DINA | E7: ='Respuestas de formulario 1'!E1158 -> THP849 | F7: ='Respuestas de formulario 1'!F1158 -> 133123 | G7: ='Respuestas de formulario 1'!G1158 -> DIURNA | H7: ='Respuestas de formulario 1'!H1158 -> CUMPLE | ... BB7: ='Respuestas de formulario 1'!BB1158 -> No
A8: ='Respuestas de formulario 1'!A1159 -> 45931.29 | B8: ='Respuestas de formulario 1'!B1159 -> Jorge Mosquera | C8: ='Respuestas de formulario 1'!C1159 -> OPERACIÓN | D8: ='Respuestas de formulario 1'!D1159 -> TELLO | E8: ='Respuestas de formulario 1'!E1159 -> NTQ466 | F8: ='Respuestas de formulario 1'!F1159 -> 7280 | G8: ='Respuestas de formulario 1'!G1159 -> DIURNA | H8: ='Respuestas de formulario 1'!H1159 -> CUMPLE | ... BB8: ='Respuestas de formulario 1'!BB1159 -> No
A9: ='Respuestas de formulario 1'!A1160 -> 45931.291 | B9: ='Respuestas de formulario 1'!B1160 -> Willin greey puentes saenz | C9: ='Respuestas de formulario 1'!C1160 -> OPERACIÓN | D9: ='Respuestas de formulario 1'!D1160 -> SAN FRANCISCO | E9: ='Respuestas de formulario 1'!E1160 -> WPT277 | F9: ='Respuestas de formulario 1'!F1160 -> 73744 | G9: ='Respuestas de formulario 1'!G1160 -> DIURNA | H9: ='Respuestas de formulario 1'!H1160 -> CUMPLE | ... BB9: ='Respuestas de formulario 1'!BB1160 -> No
A10: ='Respuestas de formulario 1'!A1161 -> 45931.292 | B10: ='Respuestas de formulario 1'!B1161 -> Aldemar González lasso | C10: ='Respuestas de formulario 1'!C1161 -> MANTENIMIENTO (CONSORCIO SAS-CFP) | D10: ='Respuestas de formulario 1'!D1161 -> SAN FRANCISCO | E10: ='Respuestas de formulario 1'!E1161 -> THS530 | F10: ='Respuestas de formulario 1'!F1161 -> 58349 | G10: ='Respuestas de formulario 1'!G1161 -> DIURNA | H10: ='Respuestas de formulario 1'!H1161 -> CUMPLE | ... BB10: ='Respuestas de formulario 1'!BB1161 -> No
A11: ='Respuestas de formulario 1'!A1162 -> 45931.294 | B11: ='Respuestas de formulario 1'!B1162 -> Wilver Collazos Quiroga | C11: ='Respuestas de formulario 1'!C1162 -> MANTENIMIENTO (CONSORCIO SAS-CFP) | D11: ='Respuestas de formulario 1'!D1162 -> DINA | E11: ='Respuestas de formulario 1'!E1162 -> LPZ104 | F11: ='Respuestas de formulario 1'!F1162 -> 40064 | G11: ='Respuestas de formulario 1'!G1162 -> DIURNA | H11: ='Respuestas de formulario 1'!H1162 -> CUMPLE | ... BB11: ='Respuestas de formulario 1'!BB1162 -> No
A12: ='Respuestas de formulario 1'!A1163 -> 45931.297 | B12: ='Respuestas de formulario 1'!B1163 -> Carlos Andrés Cabrera | C12: ='Respuestas de formulario 1'!C1163 -> OPERACIÓN | D12: ='Respuestas de formulario 1'!D1163 -> SAN FRANCISCO | E12: ='Respuestas de formulario 1'!E1163 -> THQ021 | F12: ='Respuestas de formulario 1'!F1163 -> 94720 | G12: ='Respuestas de formulario 1'!G1163 -> DIURNA | H12: ='Respuestas de formulario 1'!H1163 -> CUMPLE | ... BB12: ='Respuestas de formulario 1'!BB1163 -> No
A13: ='Respuestas de formulario 1'!A1164 -> 45931.299 | B13: ='Respuestas de formulario 1'!B1164 -> Gerardo ariza | C13: ='Respuestas de formulario 1'!C1164 -> MANTENIMIENTO (CONSORCIO SAS-CFP) | D13: ='Respuestas de formulario 1'!D1164 -> DINA | E13: ='Respuestas de formulario 1'!E1164 -> EQZ742 | F13: ='Respuestas de formulario 1'!F1164 -> 99980 | G13: ='Respuestas de formulario 1'!G1164 -> DIURNA | H13: ='Respuestas de formulario 1'!H1164 -> CUMPLE | ... BB13: ='Respuestas de formulario 1'!BB1164 -> No
... A194: ='Respuestas de formulario 1'!A1345 -> 0 | B194: ='Respuestas de formulario 1'!B1345 -> 0 | C194: ='Respuestas de formulario 1'!C1345 -> 0 | D194: ='Respuestas de formulario 1'!D1345 -> 0 | E194: ='Respuestas de formulario 1'!E1345 -> 0 | F194: ='Respuestas de formulario 1'!F1345 -> 0 | G194: ='Respuestas de formulario 1'!G1345 -> 0 | H194: ='Respuestas de formulario 1'!H1345 -> 0 | ... BB194: ='Respuestas de formulario 1'!BB1345 -> 0

Sheet SEPTIEMBRE
A1: Marca temporal | B1: NOMBRE DE QUIEN REALIZA LA INSPECCIÓN | C1: CONTRATO | D1: CAMPO/COORDINACIÓN | E1: PLACA DEL VEHICULO | F1: KILOMETRAJE | G1: TURNO | H1: **Altas y bajas | I1: **Direccionales derecha e izquierda | J1: **De parqueo | K1: **De freno | L1: **De reversa y alarma de retroceso | M1: **Espejo central y espejos laterales | N1: **Vidrio frontal | O1: Presentación de orden y aseo | P1: Pito | Q1: Sistema de monitoreo GPS (Alerta sonora) | R1: **Cinturones de seguridad | S1: Puertas en buen estado | T1: Vidrios en buen estado | U1: Limpia brisas | V1: Exintor vigente | W1: Botiquín | X1: Estado general de tapicería | Y1: Indicadores (nivel de combustible, temperatura, velocímetro y aceite) | Z1: **Verificar la ausencia de objetos sueltos en la cabina que puedan distraer al conductor | AA1: **Frenos | AB1: **Freno de emergencia o de mano | AC1: **Fugas de aire (movil 100) | AD1: **Control fugas de aire (movil 100) | AE1: **Candados y Bandas (movil 100) | AF1: **Acoples para tomas eléctricas y de aire (movil 100) | AG1: **Niveles de fluidos aceite motor | AH1: **Nivel de fluido de frenos | AI1: **Nivel de fluido de dirección hidraúlica | AJ1: **Nivel de fluido refrigerante | AK1: Nivel de fluido limpia parabrisas | AL1: Estado de correas | AM1: Estado de baterías, cables, conexiones | AN1: **Llantas - Labrado (min 3mm de labrado) | AO1: **Llantas - Sin cortaduras y sin abultamientos | AP1: Llanta de repuesto | AQ1: **Copas o pernos de sujeción de las llantas | AR1: **Suspensión (terminales) | AS1: **Dirección (terminales) | AT1: Tapa de tanque de combustible en buen estado | AU1: Equipo de carretera: gato, llave de pernos, herramienta básica, triángulos o conos, bloques, chaleco, señal pare-siga | AV1: Kit ambiental | AW1: Documentación: tecnomecánica y de gases, tarjeta de propiedad, SOAT, licencia de conducción y permiso para conducir interno | AX1: OBSERVACIONES | AY1: ¿Ha dormido al menos 7 horas en las últimas 24 horas? | AZ1: ¿Se encuentra libre de síntomas de fatiga (Somnolencia, dolor de cabeza, irritabilidad)? | BA1: ¿Se siente en condiciones físicas y mentales para conducir? | BB1: ¿Ha consumido medicamentos o sustancias que afecten su estado de alerta?
A2: ='Respuestas de formulario 1'!A658 -> 45901.236 | B2: ='Respuestas de formulario 1'!B658 -> Yoannes Rivas | C2: ='Respuestas de formulario 1'!C658 -> MANTENIMIENTO (CONSORCIO SAS-CFP) | D2: ='Respuestas de formulario 1'!D658 -> SAN FRANCISCO | E2: ='Respuestas de formulario 1'!E658 -> THS530 | F2: ='Respuestas de formulario 1'!F658 -> 56907 | G2: ='Respuestas de formulario 1'!G658 -> DIURNA | H2: ='Respuestas de formulario 1'!H658 -> CUMPLE | ... BB2: ='Respuestas de formulario 1'!BB658 -> No
A3: ='Respuestas de formulario 1'!A659 -> 45901.259 | B3: ='Respuestas de formulario 1'!B659 -> José Leonardo Castro P | C3: ='Respuestas de formulario 1'!C659 -> MANTENIMIENTO (CONSORCIO SAS-CFP) | D3: ='Respuestas de formulario 1'!D659 -> DINA | E3: ='Respuestas de formulario 1'!E659 -> WPT239 | F3: ='Respuestas de formulario 1'!F659 -> 106509 | G3: ='Respuestas de formulario 1'!G659 -> DIURNA | H3: ='Respuestas de formulario 1'!H659 -> CUMPLE | ... BB3: ='Respuestas de formulario 1'!BB659 -> No
A4: ='Respuestas de formulario 1'!A660 -> 45901.261 | B4: ='Respuestas de formulario 1'!B660 -> Carlos Alberto Huepe | C4: ='Respuestas de formulario 1'!C660 -> MANTENIMIENTO (CONSORCIO SAS-CFP) | D4: ='Respuestas de formulario 1'!D660 -> TELLO | E4: ='Respuestas de formulario 1'!E660 -> THS082 | F4: ='Respuestas de formulario 1'!F660 -> 176126 | G4: ='Respuestas de formulario 1'!G660 -> DIURNA | H4: ='Respuestas de formulario 1'!H660 -> CUMPLE | ... BB4: ='Respuestas de formulario 1'!BB660 -> Si, No
A5: ='Respuestas de formulario 1'!A661 -> 45901.262 | B5: ='Respuestas de formulario 1'!B661 -> Arbey trujillo Castro | C5: ='Respuestas de formulario 1'!C661 -> OPERACIÓN | D5: ='Respuestas de formulario 1'!D661 -> YAGUARA | E5: ='Respuestas de formulario 1'!E661 -> Wcz611 | F5: ='Respuestas de formulario 1'!F661 -> 83747 | G5: ='Respuestas de formulario 1'!G661 -> DIURNA | H5: ='Respuestas de formulario 1'!H661 -> CUMPLE | ... BB5: ='Respuestas de formulario 1'!BB661 -> No
A6: ='Respuestas de formulario 1'!A662 -> 45901.272 | B6: ='Respuestas de formulario 1'!B662 -> Jhoan Tamayo Perdomo | C6: ='Respuestas de formulario 1'!C662 -> OPERACIÓN | D6: ='Respuestas de formulario 1'!D662 -> YAGUARA | E6: ='Respuestas de formulario 1'!E662 -> THS412 | F6: ='Respuestas de formulario 1'!F662 -> 38843 | G6: ='Respuestas de formulario 1'!G662 -> NO APLICA | H6: ='Respuestas de formulario 1'!H662 -> CUMPLE | ... BB6: ='Respuestas de formulario 1'!BB662 -> No
A7: ='Respuestas de formulario 1'!A663 -> 45901.281 | B7: ='Respuestas de formulario 1'!B663 -> Jonh edinsson Charry Villarreal | C7: ='Respuestas de formulario 1'!C663 -> OPERACIÓN | D7: ='Respuestas de formulario 1'!D663 -> DINA | E7: ='Respuestas de formulario 1'!E663 -> THQ-137 | F7: ='Respuestas de formulario 1'!F663 -> 85723 | G7: ='Respuestas de formulario 1'!G663 -> DIURNA | H7: ='Respuestas de formulario 1'!H663 -> CUMPLE | ... BB7: ='Respuestas de formulario 1'!BB663 -> No
A8: ='Respuestas de formulario 1'!A664 -> 45901.281 | B8: ='Respuestas de formulario 1'!B664 -> Willin Greey Puentes saenz | C8: ='Respuestas de formulario 1'!C664 -> OPERACIÓN | D8: ='Respuestas de formulario 1'!D664 -> SAN FRANCISCO | E8: ='Respuestas de formulario 1'!E664 -> WPT 277 | F8: ='Respuestas de formulario 1'!F664 -> 72421 | G8: ='Respuestas de formulario 1'!G664 -> DIURNA | H8: ='Respuestas de formulario 1'!H664 -> CUMPLE | ... BB8: ='Respuestas de formulario 1'!BB664 -> No
A9: ='Respuestas de formulario 1'!A665 -> 45901.287 | B9: ='Respuestas de formulario 1'!B665 -> Capitolino mateus | C9: ='Respuestas de formulario 1'!C665 -> MANTENIMIENTO (CONSORCIO SAS-CFP) | D9: ='Respuestas de formulario 1'!D665 -> DINA | E9: ='Respuestas de formulario 1'!E665 -> Eqz286 | F9: ='Respuestas de formulario 1'!F665 -> 97426 | G9: ='Respuestas de formulario 1'!G665 -> DIURNA | H9: ='Respuestas de formulario 1'!H665 -> CUMPLE | ... BB9: ='Respuestas de formulario 1'!BB665 -> No
A10: ='Respuestas de formulario 1'!A666 -> 45901.288 | B10: ='Respuestas de formulario 1'!B666 -> Duvier Alberto Canacue | C10: ='Respuestas de formulario 1'!C666 -> OPERACIÓN | D10: ='Respuestas de formulario 1'!D666 -> SAN FRANCISCO | E10: ='Respuestas de formulario 1'!E666 -> Wpt243 | F10: ='Respuestas de formulario 1'!F666 -> 97374 | G10: ='Respuestas de formulario 1'!G666 -> DIURNA | H10: ='Respuestas de formulario 1'!H666 -> CUMPLE | ... BB10: ='Respuestas de formulario 1'!BB666 -> No
A11: ='Respuestas de formulario 1'!A667 -> 45901.304 | B11: ='Respuestas de formulario 1'!B667 -> Miller Jesús charry | C11: ='Respuestas de formulario 1'!C667 -> OPERACIÓN | D11: ='Respuestas de formulario 1'!D667 -> SAN FRANCISCO | E11: ='Respuestas de formulario 1'!E667 -> THQ 020 | F11: ='Respuestas de formulario 1'!F667 -> 75195 | G11: ='Respuestas de formulario 1'!G667 -> DIURNA | H11: ='Respuestas de formulario 1'!H667 -> CUMPLE | ... BB11: ='Respuestas de formulario 1'!BB667 -> No
A12: ='Respuestas de formulario 1'!A668 -> 45901.325 | B12: ='Respuestas de formulario 1'!B668 -> Jorge Lasso diaz | C12: ='Respuestas de formulario 1'!C668 -> OPERACIÓN | D12: ='Respuestas de formulario 1'!D668 -> DINA | E12: ='Respuestas de formulario 1'!E668 -> THQ 136 | F12: ='Respuestas de formulario 1'!F668 -> 72446 | G12: ='Respuestas de formulario 1'!G668 -> DIURNA | H12: ='Respuestas de formulario 1'!H668 -> CUMPLE | ... BB12: ='Respuestas de formulario 1'!BB668 -> No
A13: ='Respuestas de formulario 1'!A669 -> 45901.331 | B13: ='Respuestas de formulario 1'!B669 -> Gerardo ariza | C13: ='Respuestas de formulario 1'!C669 -> MANTENIMIENTO (CONSORCIO SAS-CFP) | D13: ='Respuestas de formulario 1'!D669 -> DINA | E13: ='Respuestas de formulario 1'!E669 -> EQZ742 | F13: ='Respuestas de formulario 1'!F669 -> 98740 | G13: ='Respuestas de formulario 1'!G669 -> DIURNA | H13: ='Respuestas de formulario 1'!H669 -> CUMPLE | ... BB13: ='Respuestas de formulario 1'!BB669 -> No
... A496: ='Respuestas de formulario 1'!A1152 -> 45930.435 | B496: ='Respuestas de formulario 1'!B1152 -> Jorge Mosquera | C496: ='Respuestas de formulario 1'!C1152 -> OPERACIÓN | D496: ='Respuestas de formulario 1'!D1152 -> TELLO | E496: ='Respuestas de formulario 1'!E1152 -> NTQ466 | F496: ='Respuestas de formulario 1'!F1152 -> 7231 | G496: ='Respuestas de formulario 1'!G1152 -> DIURNA | H496: ='Respuestas de formulario 1'!H1152 -> CUMPLE | ... BB496: ='Respuestas de formulario 1'!BB1152 -> No
